Workbook

Sheet Dashboard
A1: DASHBOARD —
A2: banca inicial
A3: 2160
A4: =$A$3+SUM(Registro!J5:J604) -> 2962.87 | C4: =IFERROR(SUM(Registro!J5:J604),0) -> 802.87 | E4: =IFERROR(C4/$A$3,0) -> 0.37169907 | G4: =COUNTIFS(Registro!A5:A604,"<>",Registro!B5:B604,"<>") -> 508 | I4: =IFERROR(AVERAGEIFS(Registro!F5:F604,Registro!I5:I604,"<>Pendiente",Registro!B5:B604,"<>"),0) -> 1.8058636 | K4: =IFERROR(AVERAGEIFS(Registro!G5:G604,Registro!I5:I604,"<>Pendiente",Registro!B5:B604,"<>"),0) -> 21.351779 | M4: =IFERROR(MIN(Registro!Q5:Q604),0) -> -158.62 | O4: =IFERROR(C4/SUMIF(Registro!I5:I604,"<>Pendiente",Registro!G5:G604),0) -> 0.074312292 | Q4: =IFERROR(M4/MAX(Registro!P5:P604),0) -> -0.05480143
A7: BANK ACTUAL (€) | C7: BENEFICIO TOTAL (€) | E7: ROI GLOBAL | G7: APUESTAS TOTALES | I7: CUOTA MEDIA | K7: STAKE MEDIO (€) | M7: DRAWDOWN MÁXIMO (€) | O7: YIELD | Q7: DRAWDOWN %
A9: RESUMEN POR CASA
A10: Casa | B10: Bank inicial (€) | C10: Beneficio (€) | D10: Bank actual (€) | E10: ROI casa | F10: Apuestas totales | G10: Ganadas | H10: Perdidas | I10: Anuladas | J10: Pendientes | K10: Win rate | L10: Cuota media | M10: Stake medio (€) | N10: Beneficio medio (€) | O10: Apuestas HOY | P10: Límite 10/día
A11: Winamax | B11: 260 | C11: =IFERROR(SUMIF(Registro!B$5:B$604,A11,Registro!J$5:J$604),0) -> 180.77 | D11: =B11+C11 -> 440.77 | E11: =IFERROR(C11/B11,0) -> 0.69526923 | F11: =COUNTIFS(Registro!B$5:B$604,A11,Registro!A$5:A$604,"<>") -> 100 | G11: =COUNTIFS(Registro!B$5:B$604,A11,Registro!I$5:I$604,"Ganada") -> 54 | H11: =COUNTIFS(Registro!B$5:B$604,A11,Registro!I$5:I$604,"Perdida") -> 37 | I11: =COUNTIFS(Registro!B$5:B$604,A11,Registro!I$5:I$604,"Anulada") -> 8 | J11: =COUNTIFS(Registro!B$5:B$604,A11,Registro!I$5:I$604,"Pendiente") -> 1 | K11: =IFERROR(G11/(G11+H11),0) -> 0.59340659 | L11: =IFERROR(AVERAGEIFS(Registro!F$5:F$604,Registro!B$5:B$604,A11),0) -> 1.7805 | M11: =IFERROR(AVERAGEIFS(Registro!G$5:G$604,Registro!B$5:B$604,A11),0) -> 23.89 | N11: =IFERROR(AVERAGEIFS(Registro!J$5:J$604,Registro!B$5:B$604,A11,Registro!I$5:I$604,"<>Pendiente"),0) -> 1.8259596 | O11: =COUNTIFS(Registro!B$5:B$604,A11,Registro!A$5:A$604,TODAY()) -> 6 | P11: =IF(O11>=10,"🔴 LÍMITE",IF(O11>=8,"🟠 CERCA","🟢 OK")) -> 🟢 OK
A12: Yosport | B12: 200 | C12: =IFERROR(SUMIF(Registro!B$5:B$604,A12,Registro!J$5:J$604),0) -> 108.84 | D12: =B12+C12 -> 308.84 | E12: =IFERROR(C12/B12,0) -> 0.5442 | F12: =COUNTIFS(Registro!B$5:B$604,A12,Registro!A$5:A$604,"<>") -> 24 | G12: =COUNTIFS(Registro!B$5:B$604,A12,Registro!I$5:I$604,"Ganada") -> 19 | H12: =COUNTIFS(Registro!B$5:B$604,A12,Registro!I$5:I$604,"Perdida") -> 5 | I12: =COUNTIFS(Registro!B$5:B$604,A12,Registro!I$5:I$604,"Anulada") -> 0 | J12: =COUNTIFS(Registro!B$5:B$604,A12,Registro!I$5:I$604,"Pendiente") -> 0 | K12: =IFERROR(G12/(G12+H12),0) -> 0.79166667 | L12: =IFERROR(AVERAGEIFS(Registro!F$5:F$604,Registro!B$5:B$604,A12),0) -> 1.5995833 | M12: =IFERROR(AVERAGEIFS(Registro!G$5:G$604,Registro!B$5:B$604,A12),0) -> 21.083333 | N12: =IFERROR(AVERAGEIFS(Registro!J$5:J$604,Registro!B$5:B$604,A12,Registro!I$5:I$604,"<>Pendiente"),0) -> 4.535 | O12: =COUNTIFS(Registro!B$5:B$604,A12,Registro!A$5:A$604,TODAY()) -> 0 | P12: =IF(O12>=10,"🔴 LÍMITE",IF(O12>=8,"🟠 CERCA","🟢 OK")) -> 🟢 OK
A13: Paf | B13: 200 | C13: =IFERROR(SUMIF(Registro!B$5:B$604,A13,Registro!J$5:J$604),0) -> 51.42 | D13: =B13+C13 -> 251.42 | E13: =IFERROR(C13/B13,0) -> 0.2571 | F13: =COUNTIFS(Registro!B$5:B$604,A13,Registro!A$5:A$604,"<>") -> 100 | G13: =COUNTIFS(Registro!B$5:B$604,A13,Registro!I$5:I$604,"Ganada") -> 58 | H13: =COUNTIFS(Registro!B$5:B$604,A13,Registro!I$5:I$604,"Perdida") -> 39 | I13: =COUNTIFS(Registro!B$5:B$604,A13,Registro!I$5:I$604,"Anulada") -> 3 | J13: =COUNTIFS(Registro!B$5:B$604,A13,Registro!I$5:I$604,"Pendiente") -> 0 | K13: =IFERROR(G13/(G13+H13),0) -> 0.59793814 | L13: =IFERROR(AVERAGEIFS(Registro!F$5:F$604,Registro!B$5:B$604,A13),0) -> 1.7959 | M13: =IFERROR(AVERAGEIFS(Registro!G$5:G$604,Registro!B$5:B$604,A13),0) -> 20.79 | N13: =IFERROR(AVERAGEIFS(Registro!J$5:J$604,Registro!B$5:B$604,A13,Registro!I$5:I$604,"<>Pendiente"),0) -> 0.5142 | O13: =COUNTIFS(Registro!B$5:B$604,A13,Registro!A$5:A$604,TODAY()) -> 10 | P13: =IF(O13>=10,"🔴 LÍMITE",IF(O13>=8,"🟠 CERCA","🟢 OK")) -> 🔴 LÍMITE
A14: Pokerstars | B14: 200 | C14: =IFERROR(SUMIF(Registro!B$5:B$604,A14,Registro!J$5:J$604),0) -> 128.46 | D14: =B14+C14 -> 328.46 | E14: =IFERROR(C14/B14,0) -> 0.6423 | F14: =COUNTIFS(Registro!B$5:B$604,A14,Registro!A$5:A$604,"<>") -> 57 | G14: =COUNTIFS(Registro!B$5:B$604,A14,Registro!I$5:I$604,"Ganada") -> 33 | H14: =COUNTIFS(Registro!B$5:B$604,A14,Registro!I$5:I$604,"Perdida") -> 24 | I14: =COUNTIFS(Registro!B$5:B$604,A14,Registro!I$5:I$604,"Anulada") -> 0 | J14: =COUNTIFS(Registro!B$5:B$604,A14,Registro!I$5:I$604,"Pendiente") -> 0 | K14: =IFERROR(G14/(G14+H14),0) -> 0.57894737 | L14: =IFERROR(AVERAGEIFS(Registro!F$5:F$604,Registro!B$5:B$604,A14),0) -> 1.9115789 | M14: =IFERROR(AVERAGEIFS(Registro!G$5:G$604,Registro!B$5:B$604,A14),0) -> 16.526316 | N14: =IFERROR(AVERAGEIFS(Registro!J$5:J$604,Registro!B$5:B$604,A14,Registro!I$5:I$604,"<>Pendiente"),0) -> 2.2536842 | O14: =COUNTIFS(Registro!B$5:B$604,A14,Registro!A$5:A$604,TODAY()) -> 3 | P14: =IF(O14>=10,"🔴 LÍMITE",IF(O14>=8,"🟠 CERCA","🟢 OK")) -> 🟢 OK
A15: Sportium | B15: 100 | C15: =IFERROR(SUMIF(Registro!B$5:B$604,A15,Registro!J$5:J$604),0) -> 169.8 | D15: =B15+C15 -> 269.8 | E15: =IFERROR(C15/B15,0) -> 1.698 | F15: =COUNTIFS(Registro!B$5:B$604,A15,Registro!A$5:A$604,"<>") -> 74 | G15: =COUNTIFS(Registro!B$5:B$604,A15,Registro!I$5:I$604,"Ganada") -> 46 | H15: =COUNTIFS(Registro!B$5:B$604,A15,Registro!I$5:I$604,"Perdida") -> 26 | I15: =COUNTIFS(Registro!B$5:B$604,A15,Registro!I$5:I$604,"Anulada") -> 2 | J15: =COUNTIFS(Registro!B$5:B$604,A15,Registro!I$5:I$604,"Pendiente") -> 0 | K15: =IFERROR(G15/(G15+H15),0) -> 0.63888889 | L15: =IFERROR(AVERAGEIFS(Registro!F$5:F$604,Registro!B$5:B$604,A15),0) -> 1.7429324 | M15: =IFERROR(AVERAGEIFS(Registro!G$5:G$604,Registro!B$5:B$604,A15),0) -> 22.72973 | N15: =IFERROR(AVERAGEIFS(Registro!J$5:J$604,Registro!B$5:B$604,A15,Registro!I$5:I$604,"<>Pendiente"),0) -> 2.2945946 | O15: =COUNTIFS(Registro!B$5:B$604,A15,Registro!A$5:A$604,TODAY()) -> 2 | P15: =IF(O15>=10,"🔴 LÍMITE",IF(O15>=8,"🟠 CERCA","🟢 OK")) -> 🟢 OK
A16: SpeedyBet | B16: 100 | C16: =IFERROR(SUMIF(Registro!B$5:B$604,A16,Registro!J$5:J$604),0) -> -88.3 | D16: =B16+C16 -> 11.7 | E16: =IFERROR(C16/B16,0) -> -0.883 | F16: =COUNTIFS(Registro!B$5:B$604,A16,Registro!A$5:A$604,"<>") -> 61 | G16: =COUNTIFS(Registro!B$5:B$604,A16,Registro!I$5:I$604,"Ganada") -> 32 | H16: =COUNTIFS(Registro!B$5:B$604,A16,Registro!I$5:I$604,"Perdida") -> 28 | I16: =COUNTIFS(Registro!B$5:B$604,A16,Registro!I$5:I$604,"Anulada") -> 0 | J16: =COUNTIFS(Registro!B$5:B$604,A16,Registro!I$5:I$604,"Pendiente") -> 1 | K16: =IFERROR(G16/(G16+H16),0) -> 0.53333333 | L16: =IFERROR(AVERAGEIFS(Registro!F$5:F$604,Registro!B$5:B$604,A16),0) -> 1.8413115 | M16: =IFERROR(AVERAGEIFS(Registro!G$5:G$604,Registro!B$5:B$604,A16),0) -> 20.47541 | N16: =IFERROR(AVERAGEIFS(Registro!J$5:J$604,Registro!B$5:B$604,A16,Registro!I$5:I$604,"<>Pendiente"),0) -> -1.4716667 | O16: =COUNTIFS(Registro!B$5:B$604,A16,Registro!A$5:A$604,TODAY()) -> 2 | P16: =IF(O16>=10,"🔴 LÍMITE",IF(O16>=8,"🟠 CERCA","🟢 OK")) -> 🟢 OK
A17: Casumo | B17: 17.69 | C17: =IFERROR(SUMIF(Registro!B$5:B$604,A17,Registro!J$5:J$604),0) -> 166.3 | D17: =B17+C17 -> 183.99 | E17: =IFERROR(C17/B17,0) -> 9.4007914 | F17: =COUNTIFS(Registro!B$5:B$604,A17,Registro!A$5:A$604,"<>") -> 20 | G17: =COUNTIFS(Registro!B$5:B$604,A17,Registro!I$5:I$604,"Ganada") -> 16 | H17: =COUNTIFS(Registro!B$5:B$604,A17,Registro!I$5:I$604,"Perdida") -> 3 | I17: =COUNTIFS(Registro!B$5:B$604,A17,Registro!I$5:I$604,"Anulada") -> 1 | J17: =COUNTIFS(Registro!B$5:B$604,A17,Registro!I$5:I$604,"Pendiente") -> 0 | K17: =IFERROR(G17/(G17+H17),0) -> 0.84210526 | L17: =IFERROR(AVERAGEIFS(Registro!F$5:F$604,Registro!B$5:B$604,A17),0) -> 1.594 | M17: =IFERROR(AVERAGEIFS(Registro!G$5:G$604,Registro!B$5:B$604,A17),0) -> 28.8 | N17: =IFERROR(AVERAGEIFS(Registro!J$5:J$604,Registro!B$5:B$604,A17,Registro!I$5:I$604,"<>Pendiente"),0) -> 8.315 | O17: =COUNTIFS(Registro!B$5:B$604,A17,Registro!A$5:A$604,TODAY()) -> 0 | P17: =IF(O17>=10,"🔴 LÍMITE",IF(O17>=8,"🟠 CERCA","🟢 OK")) -> 🟢 OK
A18: Retabet | B18: 0 | C18: =IFERROR(SUMIF(Registro!B$5:B$604,A18,Registro!J$5:J$604),0) -> 0 | D18: =B18+C18 -> 0 | E18: =IFERROR(C18/B18,0) -> 0 | F18: =COUNTIFS(Registro!B$5:B$604,A18,Registro!A$5:A$604,"<>") -> 0 | G18: =COUNTIFS(Registro!B$5:B$604,A18,Registro!I$5:I$604,"Ganada") -> 0 | H18: =COUNTIFS(Registro!B$5:B$604,A18,Registro!I$5:I$604,"Perdida") -> 0 | I18: =COUNTIFS(Registro!B$5:B$604,A18,Registro!I$5:I$604,"Anulada") -> 0 | J18: =COUNTIFS(Registro!B$5:B$604,A18,Registro!I$5:I$604,"Pendiente") -> 0 | K18: =IFERROR(G18/(G18+H18),0) -> 0 | L18: =IFERROR(AVERAGEIFS(Registro!F$5:F$604,Registro!B$5:B$604,A18),0) -> 0 | M18: =IFERROR(AVERAGEIFS(Registro!G$5:G$604,Registro!B$5:B$604,A18),0) -> 0 | N18: =IFERROR(AVERAGEIFS(Registro!J$5:J$604,Registro!B$5:B$604,A18,Registro!I$5:I$604,"<>Pendiente"),0) -> 0 | O18: =COUNTIFS(Registro!B$5:B$604,A18,Registro!A$5:A$604,TODAY()) -> 0 | P18: =IF(O18>=10,"🔴 LÍMITE",IF(O18>=8,"🟠 CERCA","🟢 OK")) -> 🟢 OK
A19: GoldenBull | B19: 100 | C19: =IFERROR(SUMIF(Registro!B$5:B$604,A19,Registro!J$5:J$604),0) -> 133.4 | D19: =B19+C19 -> 233.4 | E19: =IFERROR(C19/B19,0) -> 1.334 | F19: =COUNTIFS(Registro!B$5:B$604,A19,Registro!A$5:A$604,"<>") -> 64 | G19: =COUNTIFS(Registro!B$5:B$604,A19,Registro!I$5:I$604,"Ganada") -> 39 | H19: =COUNTIFS(Registro!B$5:B$604,A19,Registro!I$5:I$604,"Perdida") -> 25 | I19: =COUNTIFS(Registro!B$5:B$604,A19,Registro!I$5:I$604,"Anulada") -> 0 | J19: =COUNTIFS(Registro!B$5:B$604,A19,Registro!I$5:I$604,"Pendiente") -> 0 | K19: =IFERROR(G19/(G19+H19),0) -> 0.609375 | L19: =IFERROR(AVERAGEIFS(Registro!F$5:F$604,Registro!B$5:B$604,A19),0) -> 1.915625 | M19: =IFERROR(AVERAGEIFS(Registro!G$5:G$604,Registro!B$5:B$604,A19),0) -> 20.328125 | N19: =IFERROR(AVERAGEIFS(Registro!J$5:J$604,Registro!B$5:B$604,A19,Registro!I$5:I$604,"<>Pendiente"),0) -> 2.084375 | O19: =COUNTIFS(Registro!B$5:B$604,A19,Registro!A$5:A$604,TODAY()) -> 0 | P19: =IF(O19>=10,"🔴 LÍMITE",IF(O19>=8,"🟠 CERCA","🟢 OK")) -> 🟢 OK
A20: Bet365 | B20: 55 | C20: =IFERROR(SUMIF(Registro!B$5:B$604,A20,Registro!J$5:J$604),0) -> -47.82 | D20: =B20+C20 -> 7.18 | F20: =COUNTIFS(Registro!B$5:B$604,A20,Registro!A$5:A$604,"<>") -> 8 | G20: =COUNTIFS(Registro!B$5:B$604,A20,Registro!I$5:I$604,"Ganada") -> 3 | H20: =COUNTIFS(Registro!B$5:B$604,A20,Registro!I$5:I$604,"Perdida") -> 4 | I20: =COUNTIFS(Registro!B$5:B$604,A20,Registro!I$5:I$604,"Anulada") -> 1 | J20: =COUNTIFS(Registro!B$5:B$604,A20,Registro!I$5:I$604,"Pendiente") -> 0 | K20: =IFERROR(G20/(G20+H20),0) -> 0.42857143 | L20: =IFERROR(AVERAGEIFS(Registro!F$5:F$604,Registro!B$5:B$604,A20),0) -> 2.03375 | M20: =IFERROR(AVERAGEIFS(Registro!G$5:G$604,Registro!B$5:B$604,A20),0) -> 17.5 | N20: =IFERROR(AVERAGEIFS(Registro!J$5:J$604,Registro!B$5:B$604,A20,Registro!I$5:I$604,"<>Pendiente"),0) -> -5.9775 | O20: =COUNTIFS(Registro!B$5:B$604,A20,Registro!A$5:A$604,TODAY()) -> 0 | P20: =IF(O20>=10,"🔴 LÍMITE",IF(O20>=8,"🟠 CERCA","🟢 OK")) -> 🟢 OK
A21: Botemania | B21: 0 | C21: =IFERROR(SUMIF(Registro!B$5:B$604,A21,Registro!J$5:J$604),0) -> 0 | D21: =B21+C21 -> 0 | E21: =IFERROR(C21/B21,0) -> 0 | F21: =COUNTIFS(Registro!B$5:B$604,A21,Registro!A$5:A$604,"<>") -> 0 | G21: =COUNTIFS(Registro!B$5:B$604,A21,Registro!I$5:I$604,"Ganada") -> 0 | H21: =COUNTIFS(Registro!B$5:B$604,A21,Registro!I$5:I$604,"Perdida") -> 0 | I21: =COUNTIFS(Registro!B$5:B$604,A21,Registro!I$5:I$604,"Anulada") -> 0 | J21: =COUNTIFS(Registro!B$5:B$604,A21,Registro!I$5:I$604,"Pendiente") -> 0 | K21: =IFERROR(G21/(G21+H21),0) -> 0 | L21: =IFERROR(AVERAGEIFS(Registro!F$5:F$604,Registro!B$5:B$604,A21),0) -> 0 | M21: =IFERROR(AVERAGEIFS(Registro!G$5:G$604,Registro!B$5:B$604,A21),0) -> 0 | N21: =IFERROR(AVERAGEIFS(Registro!J$5:J$604,Registro!B$5:B$604,A21,Registro!I$5:I$604,"<>Pendiente"),0) -> 0 | O21: =COUNTIFS(Registro!B$5:B$604,A21,Registro!A$5:A$604,TODAY()) -> 0 | P21: =IF(O21>=10,"🔴 LÍMITE",IF(O21>=8,"🟠 CERCA","🟢 OK")) -> 🟢 OK
A22: Paston | B22: 0 | C22: =IFERROR(SUMIF(Registro!B$5:B$604,A22,Registro!J$5:J$604),0) -> 0 | D22: =B22+C22 -> 0 | E22: =IFERROR(C22/B22,0) -> 0 | F22: =COUNTIFS(Registro!B$5:B$604,A22,Registro!A$5:A$604,"<>") -> 0 | G22: =COUNTIFS(Registro!B$5:B$604,A22,Registro!I$5:I$604,"Ganada") -> 0 | H22: =COUNTIFS(Registro!B$5:B$604,A22,Registro!I$5:I$604,"Perdida") -> 0 | I22: =COUNTIFS(Registro!B$5:B$604,A22,Registro!I$5:I$604,"Anulada") -> 0 | J22: =COUNTIFS(Registro!B$5:B$604,A22,Registro!I$5:I$604,"Pendiente") -> 0 | K22: =IFERROR(G22/(G22+H22),0) -> 0 | L22: =IFERROR(AVERAGEIFS(Registro!F$5:F$604,Registro!B$5:B$604,A22),0) -> 0 | M22: =IFERROR(AVERAGEIFS(Registro!G$5:G$604,Registro!B$5:B$604,A22),0) -> 0 | N22: =IFERROR(AVERAGEIFS(Registro!J$5:J$604,Registro!B$5:B$604,A22,Registro!I$5:I$604,"<>Pendiente"),0) -> 0 | O22: =COUNTIFS(Registro!B$5:B$604,A22,Registro!A$5:A$604,TODAY()) -> 0 | P22: =IF(O22>=10,"🔴 LÍMITE",IF(O22>=8,"🟠 CERCA","🟢 OK")) -> 🟢 OK
A23: Casino Gran Madrid | B23: 0 | C23: =IFERROR(SUMIF(Registro!B$5:B$604,A23,Registro!J$5:J$604),0) -> 0 | D23: =B23+C23 -> 0 | E23: =IFERROR(C23/B23,0) -> 0 | F23: =COUNTIFS(Registro!B$5:B$604,A23,Registro!A$5:A$604,"<>") -> 0 | G23: =COUNTIFS(Registro!B$5:B$604,A23,Registro!I$5:I$604,"Ganada") -> 0 | H23: =COUNTIFS(Registro!B$5:B$604,A23,Registro!I$5:I$604,"Perdida") -> 0 | I23: =COUNTIFS(Registro!B$5:B$604,A23,Registro!I$5:I$604,"Anulada") -> 0 | J23: =COUNTIFS(Registro!B$5:B$604,A23,Registro!I$5:I$604,"Pendiente") -> 0 | K23: =IFERROR(G23/(G23+H23),0) -> 0 | L23: =IFERROR(AVERAGEIFS(Registro!F$5:F$604,Registro!B$5:B$604,A23),0) -> 0 | M23: =IFERROR(AVERAGEIFS(Registro!G$5:G$604,Registro!B$5:B$604,A23),0) -> 0 | N23: =IFERROR(AVERAGEIFS(Registro!J$5:J$604,Registro!B$5:B$604,A23,Registro!I$5:I$604,"<>Pendiente"),0) -> 0 | O23: =COUNTIFS(Registro!B$5:B$604,A23,Registro!A$5:A$604,TODAY()) -> 0 | P23: =IF(O23>=10,"🔴 LÍMITE",IF(O23>=8,"🟠 CERCA","🟢 OK")) -> 🟢 OK
A24: TOTAL | B24: =SUM(B11:B23) -> 1232.69 | C24: =SUM(C11:C23) -> 802.87 | D24: =B24+C24 -> 2035.56 | E24: =IFERROR(C24/$A$3,0) -> 0.37169907 | F24: =SUM(F11:F23) -> 508 | G24: =SUM(G11:G23) -> 300 | H24: =SUM(H11:H23) -> 191 | I24: =SUM(I11:I23) -> 15 | J24: =SUM(J11:J23) -> 2 | K24: =IFERROR(G24/(G24+H24),0) -> 0.61099796 | L24: =IFERROR(AVERAGEIFS(Registro!F5:F604,Registro!I5:I604,"<>Pendiente"),0) -> 1.8058636 | M24: =IFERROR(AVERAGEIFS(Registro!G5:G604,Registro!I5:I604,"<>Pendiente"),0) -> 21.351779 | N24: =IFERROR(AVERAGEIFS(Registro!J5:J604,Registro!I5:I604,"<>Pendiente"),0) -> 1.5866996 | O24: =SUM(O11:O23) -> 23
A25: 🏦 Banco (reserva) | B25: =$A$3-B24 -> 927.31 | C25: ← actualiza A3 cuando hagas ingresos
K46: 1.8
B56: Columna1
J75: Columna1

Sheet Registro
A1: REGISTRO DE APUESTAS
A2: Bank global: 1.800€ | 9 casas x 200€ | Máx. 10 apuestas/día/casa
A4: Fecha | B4: Casa | C4: Evento | D4: Mercado | E4: Selección | F4: Cuota | G4: Stake (€) | H4: Tipo | I4: Resultado | J4: Beneficio (€) | K4: Bank acum. (€) | L4: ROI apuesta | M4: Apuestas hoy (casa) | N4: Notas | O4: Nº apuesta | P4: Bank máx. acum. (€) | Q4: Drawdown (€) | R4: Importe Cash Out (€) | S4: EV+ por apuesta (€) | T4: EV+ acumulado (€)
A5: 46194 | B5: Paf | C5: Egersund - Haugesund | D5: Totales O/U | E5: corners: Menos de 10.5 | F5: 1.86 | G5: 15 | H5: Normal | I5: Ganada | J5: =IF($A5="","",IF($I5="Ganada",ROUND($G5*($F5-1),2),IF($I5="Medio Ganada",ROUND($G5/2*($F5-1),2),IF($I5="Perdida",IF($H5="Free Bet",0,-$G5),IF($I5="Medio Perdida",IF($H5="Free Bet",0,-$G5/2),IF($I5="Reembolso",IF($R5="","",ROUND($R5-$G5,2)),IF($I5="Anulada",0,""))))))) -> 12.9 | K5: =IF(J5="","",2000+SUM(J$5:J5)) -> 2012.9 | L5: =IF(OR($I5="Ganada",$I5="Perdida",$I5="Medio Ganada",$I5="Medio Perdida"),IF($G5=0,"",J5/$G5),"") -> 0.86 | M5: =IF(OR($A5="",$B5=""),"",COUNTIFS($A$5:A5,A5,$B$5:B5,B5)) -> 1 | N5: =IF($A5="","",COUNTA($A$5:$A5)) -> 1 | O5: =IF($A5="","",COUNTA($A$5:$A5)) -> 1 | P5: =IF($K5="","",MAX($K$5:K5)) -> 2012.9 | Q5: =IF($K5="","",K5-P5) -> 0 | S5: =IF(OR($A5="",$F5=""),"",IF($I5="Pendiente","",ROUND($G5*($F5*0.609-1),2))) -> 1.99 | T5: =IF($A5="","",IFERROR(SUM($S$5:S5),0)) -> 1.99
A6: 46194 | B6: Paf | C6: Raufoss - Sogndal | D6: Totales O/U | E6: corners: Más de 9.5 | F6: 1.87 | G6: 15 | H6: Normal | I6: Ganada | J6: =IF($A6="","",IF($I6="Ganada",ROUND($G6*($F6-1),2),IF($I6="Medio Ganada",ROUND($G6/2*($F6-1),2),IF($I6="Perdida",IF($H6="Free Bet",0,-$G6),IF($I6="Medio Perdida",IF($H6="Free Bet",0,-$G6/2),IF($I6="Reembolso",IF($R6="","",ROUND($R6-$G6,2)),IF($I6="Anulada",0,""))))))) -> 13.05 | K6: =IF(J6="","",2000+SUM(J$5:J6)) -> 2025.95 | L6: =IF(OR($I6="Ganada",$I6="Perdida",$I6="Medio Ganada",$I6="Medio Perdida"),IF($G6=0,"",J6/$G6),"") -> 0.87 | M6: =IF(OR($A6="",$B6=""),"",COUNTIFS($A$5:A6,A6,$B$5:B6,B6)) -> 2 | N6: =IF($A6="","",COUNTA($A$5:$A6)) -> 2 | O6: =IF($A6="","",COUNTA($A$5:$A6)) -> 2 | P6: =IF($K6="","",MAX($K$5:K6)) -> 2025.95 | Q6: =IF($K6="","",K6-P6) -> 0 | S6: =IF(OR($A6="",$F6=""),"",IF($I6="Pendiente","",ROUND($G6*($F6*0.609-1),2))) -> 2.08 | T6: =IF($A6="","",IFERROR(SUM($S$5:S6),0)) -> 4.07
A7: 46194 | B7: Paf | C7: Strømmen - Stabæk | D7: Totales O/U | E7: corners: Menos de 11.5 | F7: 1.56 | G7: 20 | H7: Normal | I7: Perdida | J7: =IF($A7="","",IF($I7="Ganada",ROUND($G7*($F7-1),2),IF($I7="Medio Ganada",ROUND($G7/2*($F7-1),2),IF($I7="Perdida",IF($H7="Free Bet",0,-$G7),IF($I7="Medio Perdida",IF($H7="Free Bet",0,-$G7/2),IF($I7="Reembolso",IF($R7="","",ROUND($R7-$G7,2)),IF($I7="Anulada",0,""))))))) -> -20 | K7: =IF(J7="","",2000+SUM(J$5:J7)) -> 2005.95 | L7: =IF(OR($I7="Ganada",$I7="Perdida",$I7="Medio Ganada",$I7="Medio Perdida"),IF($G7=0,"",J7/$G7),"") -> -1 | M7: =IF(OR($A7="",$B7=""),"",COUNTIFS($A$5:A7,A7,$B$5:B7,B7)) -> 3 | N7: =IF($A7="","",COUNTA($A$5:$A7)) -> 3 | O7: =IF($A7="","",COUNTA($A$5:$A7)) -> 3 | P7: =IF($K7="","",MAX($K$5:K7)) -> 2025.95 | Q7: =IF($K7="","",K7-P7) -> -20 | S7: =IF(OR($A7="",$F7=""),"",IF($I7="Pendiente","",ROUND($G7*($F7*0.609-1),2))) -> -1 | T7: =IF($A7="","",IFERROR(SUM($S$5:S7),0)) -> 3.07
A8: 46194 | B8: Paf | C8: Strømmen - Stabæk | D8: 1X2/ML | E8: Strømmen | F8: 1.58 | G8: 20 | H8: Normal | I8: Ganada | J8: =IF($A8="","",IF($I8="Ganada",ROUND($G8*($F8-1),2),IF($I8="Medio Ganada",ROUND($G8/2*($F8-1),2),IF($I8="Perdida",IF($H8="Free Bet",0,-$G8),IF($I8="Medio Perdida",IF($H8="Free Bet",0,-$G8/2),IF($I8="Reembolso",IF($R8="","",ROUND($R8-$G8,2)),IF($I8="Anulada",0,""))))))) -> 11.6 | K8: =IF(J8="","",2000+SUM(J$5:J8)) -> 2017.55 | L8: =IF(OR($I8="Ganada",$I8="Perdida",$I8="Medio Ganada",$I8="Medio Perdida"),IF($G8=0,"",J8/$G8),"") -> 0.58 | M8: =IF(OR($A8="",$B8=""),"",COUNTIFS($A$5:A8,A8,$B$5:B8,B8)) -> 4 | N8: =IF($A8="","",COUNTA($A$5:$A8)) -> 4 | O8: =IF($A8="","",COUNTA($A$5:$A8)) -> 4 | P8: =IF($K8="","",MAX($K$5:K8)) -> 2025.95 | Q8: =IF($K8="","",K8-P8) -> -8.4 | S8: =IF(OR($A8="",$F8=""),"",IF($I8="Pendiente","",ROUND($G8*($F8*0.609-1),2))) -> -0.76 | T8: =IF($A8="","",IFERROR(SUM($S$5:S8),0)) -> 2.31
A9: 46194 | B9: Winamax | C9: crac go- tombense mg | D9: Totales O/U | E9: menos de 2 goles | F9: 2.1 | G9: 15 | H9: Normal | I9: Ganada | J9: =IF($A9="","",IF($I9="Ganada",ROUND($G9*($F9-1),2),IF($I9="Medio Ganada",ROUND($G9/2*($F9-1),2),IF($I9="Perdida",IF($H9="Free Bet",0,-$G9),IF($I9="Medio Perdida",IF($H9="Free Bet",0,-$G9/2),IF($I9="Reembolso",IF($R9="","",ROUND($R9-$G9,2)),IF($I9="Anulada",0,""))))))) -> 16.5 | K9: =IF(J9="","",2000+SUM(J$5:J9)) -> 2034.05 | L9: =IF(OR($I9="Ganada",$I9="Perdida",$I9="Medio Ganada",$I9="Medio Perdida"),IF($G9=0,"",J9/$G9),"") -> 1.1 | M9: =IF(OR($A9="",$B9=""),"",COUNTIFS($A$5:A9,A9,$B$5:B9,B9)) -> 1 | N9: =IF($A9="","",COUNTA($A$5:$A9)) -> 5 | O9: =IF($A9="","",COUNTA($A$5:$A9)) -> 5 | P9: =IF($K9="","",MAX($K$5:K9)) -> 2034.05 | Q9: =IF($K9="","",K9-P9) -> 0 | S9: =IF(OR($A9="",$F9=""),"",IF($I9="Pendiente","",ROUND($G9*($F9*0.609-1),2))) -> 4.18 | T9: =IF($A9="","",IFERROR(SUM($S$5:S9),0)) -> 6.49
A10: 46194 | B10: Winamax | C10: R.Safiullin-J.McCabe | D10: Totales O/U | E10: +22,5 juegos | F10: 2 | G10: 15 | H10: Normal | I10: Perdida | J10: =IF($A10="","",IF($I10="Ganada",ROUND($G10*($F10-1),2),IF($I10="Medio Ganada",ROUND($G10/2*($F10-1),2),IF($I10="Perdida",IF($H10="Free Bet",0,-$G10),IF($I10="Medio Perdida",IF($H10="Free Bet",0,-$G10/2),IF($I10="Reembolso",IF($R10="","",ROUND($R10-$G10,2)),IF($I10="Anulada",0,""))))))) -> -15 | K10: =IF(J10="","",2000+SUM(J$5:J10)) -> 2019.05 | L10: =IF(OR($I10="Ganada",$I10="Perdida",$I10="Medio Ganada",$I10="Medio Perdida"),IF($G10=0,"",J10/$G10),"") -> -1 | M10: =IF(OR($A10="",$B10=""),"",COUNTIFS($A$5:A10,A10,$B$5:B10,B10)) -> 2 | N10: =IF($A10="","",COUNTA($A$5:$A10)) -> 6 | O10: =IF($A10="","",COUNTA($A$5:$A10)) -> 6 | P10: =IF($K10="","",MAX($K$5:K10)) -> 2034.05 | Q10: =IF($K10="","",K10-P10) -> -15 | S10: =IF(OR($A10="",$F10=""),"",IF($I10="Pendiente","",ROUND($G10*($F10*0.609-1),2))) -> 3.27 | T10: =IF($A10="","",IFERROR(SUM($S$5:S10),0)) -> 9.76
A11: 46194 | B11: Winamax | C11: Andrade, Andres - Smith, Connor | D11: Totales O/U | E11: Total Under(21.5) - regular time | F11: 1.9 | G11: 15 | H11: Normal | I11: Perdida | J11: =IF($A11="","",IF($I11="Ganada",ROUND($G11*($F11-1),2),IF($I11="Medio Ganada",ROUND($G11/2*($F11-1),2),IF($I11="Perdida",IF($H11="Free Bet",0,-$G11),IF($I11="Medio Perdida",IF($H11="Free Bet",0,-$G11/2),IF($I11="Reembolso",IF($R11="","",ROUND($R11-$G11,2)),IF($I11="Anulada",0,""))))))) -> -15 | K11: =IF(J11="","",2000+SUM(J$5:J11)) -> 2004.05 | L11: =IF(OR($I11="Ganada",$I11="Perdida",$I11="Medio Ganada",$I11="Medio Perdida"),IF($G11=0,"",J11/$G11),"") -> -1 | M11: =IF(OR($A11="",$B11=""),"",COUNTIFS($A$5:A11,A11,$B$5:B11,B11)) -> 3 | N11: =IF($A11="","",COUNTA($A$5:$A11)) -> 7 | O11: =IF($A11="","",COUNTA($A$5:$A11)) -> 7 | P11: =IF($K11="","",MAX($K$5:K11)) -> 2034.05 | Q11: =IF($K11="","",K11-P11) -> -30 | S11: =IF(OR($A11="",$F11=""),"",IF($I11="Pendiente","",ROUND($G11*($F11*0.609-1),2))) -> 2.36 | T11: =IF($A11="","",IFERROR(SUM($S$5:S11),0)) -> 12.12
A12: 46194 | B12: Winamax | C12: Leones De Ponce - Osos de Manati | D12: 1X2/ML | E12: Team1 Win - with OT | F12: 1.66 | G12: 20 | H12: Normal | I12: Perdida | J12: =IF($A12="","",IF($I12="Ganada",ROUND($G12*($F12-1),2),IF($I12="Medio Ganada",ROUND($G12/2*($F12-1),2),IF($I12="Perdida",IF($H12="Free Bet",0,-$G12),IF($I12="Medio Perdida",IF($H12="Free Bet",0,-$G12/2),IF($I12="Reembolso",IF($R12="","",ROUND($R12-$G12,2)),IF($I12="Anulada",0,""))))))) -> -20 | K12: =IF(J12="","",2000+SUM(J$5:J12)) -> 1984.05 | L12: =IF(OR($I12="Ganada",$I12="Perdida",$I12="Medio Ganada",$I12="Medio Perdida"),IF($G12=0,"",J12/$G12),"") -> -1 | M12: =IF(OR($A12="",$B12=""),"",COUNTIFS($A$5:A12,A12,$B$5:B12,B12)) -> 4 | N12: =IF($A12="","",COUNTA($A$5:$A12)) -> 8 | O12: =IF($A12="","",COUNTA($A$5:$A12)) -> 8 | P12: =IF($K12="","",MAX($K$5:K12)) -> 2034.05 | Q12: =IF($K12="","",K12-P12) -> -50 | S12: =IF(OR($A12="",$F12=""),"",IF($I12="Pendiente","",ROUND($G12*($F12*0.609-1),2))) -> 0.22 | T12: =IF($A12="","",IFERROR(SUM($S$5:S12),0)) -> 12.34
A13: 46194 | B13: Winamax | C13: Independencia AC - Manauara AM | D13: Totales O/U | E13: Total Under(1) - 1s | F13: 2 | G13: 15 | H13: Normal | I13: Anulada | J13: =IF($A13="","",IF($I13="Ganada",ROUND($G13*($F13-1),2),IF($I13="Medio Ganada",ROUND($G13/2*($F13-1),2),IF($I13="Perdida",IF($H13="Free Bet",0,-$G13),IF($I13="Medio Perdida",IF($H13="Free Bet",0,-$G13/2),IF($I13="Reembolso",IF($R13="","",ROUND($R13-$G13,2)),IF($I13="Anulada",0,""))))))) -> 0 | K13: =IF(J13="","",2000+SUM(J$5:J13)) -> 1984.05 | L13: =IF(OR($I13="Ganada",$I13="Perdida",$I13="Medio Ganada",$I13="Medio Perdida"),IF($G13=0,"",J13/$G13),"") | M13: =IF(OR($A13="",$B13=""),"",COUNTIFS($A$5:A13,A13,$B$5:B13,B13)) -> 5 | N13: =IF($A13="","",COUNTA($A$5:$A13)) -> 9 | O13: =IF($A13="","",COUNTA($A$5:$A13)) -> 9 | P13: =IF($K13="","",MAX($K$5:K13)) -> 2034.05 | Q13: =IF($K13="","",K13-P13) -> -50 | S13: =IF(OR($A13="",$F13=""),"",IF($I13="Pendiente","",ROUND($G13*($F13*0.609-1),2))) -> 3.27 | T13: =IF($A13="","",IFERROR(SUM($S$5:S13),0)) -> 15.61
A14: 46194 | B14: Winamax | C14: Talleres Remedios - Comunicaciones | D14: DNB | E14: AH1(0.0)/DNB | F14: 1.34 | G14: 15 | H14: Normal | I14: Anulada | J14: =IF($A14="","",IF($I14="Ganada",ROUND($G14*($F14-1),2),IF($I14="Medio Ganada",ROUND($G14/2*($F14-1),2),IF($I14="Perdida",IF($H14="Free Bet",0,-$G14),IF($I14="Medio Perdida",IF($H14="Free Bet",0,-$G14/2),IF($I14="Reembolso",IF($R14="","",ROUND($R14-$G14,2)),IF($I14="Anulada",0,""))))))) -> 0 | K14: =IF(J14="","",2000+SUM(J$5:J14)) -> 1984.05 | L14: =IF(OR($I14="Ganada",$I14="Perdida",$I14="Medio Ganada",$I14="Medio Perdida"),IF($G14=0,"",J14/$G14),"") | M14: =IF(OR($A14="",$B14=""),"",COUNTIFS($A$5:A14,A14,$B$5:B14,B14)) -> 6 | N14: =IF($A14="","",COUNTA($A$5:$A14)) -> 10 | O14: =IF($A14="","",COUNTA($A$5:$A14)) -> 10 | P14: =IF($K14="","",MAX($K$5:K14)) -> 2034.05 | Q14: =IF($K14="","",K14-P14) -> -50 | S14: =IF(OR($A14="",$F14=""),"",IF($I14="Pendiente","",ROUND($G14*($F14*0.609-1),2))) -> -2.76 | T14: =IF($A14="","",IFERROR(SUM($S$5:S14),0)) -> 12.85
A15: 46194 | B15: Winamax | C15: Klugman, Hannah - Valentova, Tereza | D15: Totales O/U | E15: Total Over(19.5) | F15: 1.86 | G15: 15 | H15: Normal | I15: Ganada | J15: =IF($A15="","",IF($I15="Ganada",ROUND($G15*($F15-1),2),IF($I15="Medio Ganada",ROUND($G15/2*($F15-1),2),IF($I15="Perdida",IF($H15="Free Bet",0,-$G15),IF($I15="Medio Perdida",IF($H15="Free Bet",0,-$G15/2),IF($I15="Reembolso",IF($R15="","",ROUND($R15-$G15,2)),IF($I15="Anulada",0,""))))))) -> 12.9 | K15: =IF(J15="","",2000+SUM(J$5:J15)) -> 1996.95 | L15: =IF(OR($I15="Ganada",$I15="Perdida",$I15="Medio Ganada",$I15="Medio Perdida"),IF($G15=0,"",J15/$G15),"") -> 0.86 | M15: =IF(OR($A15="",$B15=""),"",COUNTIFS($A$5:A15,A15,$B$5:B15,B15)) -> 7 | N15: =IF($A15="","",COUNTA($A$5:$A15)) -> 11 | O15: =IF($A15="","",COUNTA($A$5:$A15)) -> 11 | P15: =IF($K15="","",MAX($K$5:K15)) -> 2034.05 | Q15: =IF($K15="","",K15-P15) -> -37.1 | S15: =IF(OR($A15="",$F15=""),"",IF($I15="Pendiente","",ROUND($G15*($F15*0.609-1),2))) -> 1.99 | T15: =IF($A15="","",IFERROR(SUM($S$5:S15),0)) -> 14.84
A16: 46194 | B16: Winamax | C16: Jay Clarke – Andrea Pellegrino | D16: Hándicap | E16: Hándicap asiático 2 4.5 juegos | F16: 1.7 | G16: 25 | H16: Normal | I16: Ganada | J16: =IF($A16="","",IF($I16="Ganada",ROUND($G16*($F16-1),2),IF($I16="Medio Ganada",ROUND($G16/2*($F16-1),2),IF($I16="Perdida",IF($H16="Free Bet",0,-$G16),IF($I16="Medio Perdida",IF($H16="Free Bet",0,-$G16/2),IF($I16="Reembolso",IF($R16="","",ROUND($R16-$G16,2)),IF($I16="Anulada",0,""))))))) -> 17.5 | K16: =IF(J16="","",2000+SUM(J$5:J16)) -> 2014.45 | L16: =IF(OR($I16="Ganada",$I16="Perdida",$I16="Medio Ganada",$I16="Medio Perdida"),IF($G16=0,"",J16/$G16),"") -> 0.7 | M16: =IF(OR($A16="",$B16=""),"",COUNTIFS($A$5:A16,A16,$B$5:B16,B16)) -> 8 | N16: =IF($A16="","",COUNTA($A$5:$A16)) -> 12 | O16: =IF($A16="","",COUNTA($A$5:$A16)) -> 12 | P16: =IF($K16="","",MAX($K$5:K16)) -> 2034.05 | Q16: =IF($K16="","",K16-P16) -> -19.6 | S16: =IF(OR($A16="",$F16=""),"",IF($I16="Pendiente","",ROUND($G16*($F16*0.609-1),2))) -> 0.88 | T16: =IF($A16="","",IFERROR(SUM($S$5:S16),0)) -> 15.72
... A96: 46199 | B96: Paf | C96: Vaprus Pärnu - Kuressaare FC | D96: Hándicap | E96: Asian Handicap2(1.5) - regular time | F96: 1.6 | G96: 23 | H96: Normal | I96: Ganada | J96: =IF($A96="","",IF($I96="Ganada",ROUND($G96*($F96-1),2),IF($I96="Medio Ganada",ROUND($G96/2*($F96-1),2),IF($I96="Perdida",IF($H96="Free Bet",0,-$G96),IF($I96="Medio Perdida",IF($H96="Free Bet",0,-$G96/2),IF($I96="Reembolso",IF($R96="","",ROUND($R96-$G96,2)),IF($I96="Anulada",0,""))))))) -> 13.8 | K96: =IF(J96="","",2000+SUM(J$5:J96)) -> 2338.51 | L96: =IF(OR($I96="Ganada",$I96="Perdida",$I96="Medio Ganada",$I96="Medio Perdida"),IF($G96=0,"",J96/$G96),"") -> 0.6 | M96: =IF(OR($A96="",$B96=""),"",COUNTIFS($A$5:A96,A96,$B$5:B96,B96)) -> 3 | N96: =IF($A96="","",COUNTA($A$5:$A96)) -> 92 | O96: =IF($A96="","",COUNTA($A$5:$A96)) -> 92 | P96: =IF($K96="","",MAX($K$5:K96)) -> 2338.51 | Q96: =IF($K96="","",K96-P96) -> 0 | S96: =IF(OR($A96="",$F96=""),"",IF($I96="Pendiente","",ROUND($G96*($F96*0.609-1),2))) -> -0.59 | T96: =IF($A96="","",IFERROR(SUM($S$5:S96),0)) -> 127.2
A97: 46199 | B97: Paf | C97: Liepajas Metalurgs - Rigas Futbola Skola | D97: 1X2/ML | E97: 2 | F97: 1.6 | G97: 23 | H97: Normal | I97: Ganada | J97: =IF($A97="","",IF($I97="Ganada",ROUND($G97*($F97-1),2),IF($I97="Medio Ganada",ROUND($G97/2*($F97-1),2),IF($I97="Perdida",IF($H97="Free Bet",0,-$G97),IF($I97="Medio Perdida",IF($H97="Free Bet",0,-$G97/2),IF($I97="Reembolso",IF($R97="","",ROUND($R97-$G97,2)),IF($I97="Anulada",0,""))))))) -> 13.8 | K97: =IF(J97="","",2000+SUM(J$5:J97)) -> 2352.31 | L97: =IF(OR($I97="Ganada",$I97="Perdida",$I97="Medio Ganada",$I97="Medio Perdida"),IF($G97=0,"",J97/$G97),"") -> 0.6 | M97: =IF(OR($A97="",$B97=""),"",COUNTIFS($A$5:A97,A97,$B$5:B97,B97)) -> 4 | N97: =IF($A97="","",COUNTA($A$5:$A97)) -> 93 | O97: =IF($A97="","",COUNTA($A$5:$A97)) -> 93 | P97: =IF($K97="","",MAX($K$5:K97)) -> 2352.31 | Q97: =IF($K97="","",K97-P97) -> 0 | S97: =IF(OR($A97="",$F97=""),"",IF($I97="Pendiente","",ROUND($G97*($F97*0.609-1),2))) -> -0.59 | T97: =IF($A97="","",IFERROR(SUM($S$5:S97),0)) -> 126.61
A98: 46199 | B98: Yosport | C98: Lucas Andrade Da Silva - Thiago Seyboth Wild | D98: Hándicap | E98: Asian Handicap1(2.5) - regular time | F98: 1.84 | G98: 17 | H98: Normal | I98: Ganada | J98: =IF($A98="","",IF($I98="Ganada",ROUND($G98*($F98-1),2),IF($I98="Medio Ganada",ROUND($G98/2*($F98-1),2),IF($I98="Perdida",IF($H98="Free Bet",0,-$G98),IF($I98="Medio Perdida",IF($H98="Free Bet",0,-$G98/2),IF($I98="Reembolso",IF($R98="","",ROUND($R98-$G98,2)),IF($I98="Anulada",0,""))))))) -> 14.28 | K98: =IF(J98="","",2000+SUM(J$5:J98)) -> 2366.59 | L98: =IF(OR($I98="Ganada",$I98="Perdida",$I98="Medio Ganada",$I98="Medio Perdida"),IF($G98=0,"",J98/$G98),"") -> 0.84 | M98: =IF(OR($A98="",$B98=""),"",COUNTIFS($A$5:A98,A98,$B$5:B98,B98)) -> 1 | N98: =IF($A98="","",COUNTA($A$5:$A98)) -> 94 | O98: =IF($A98="","",COUNTA($A$5:$A98)) -> 94 | P98: =IF($K98="","",MAX($K$5:K98)) -> 2366.59 | Q98: =IF($K98="","",K98-P98) -> 0 | S98: =IF(OR($A98="",$F98=""),"",IF($I98="Pendiente","",ROUND($G98*($F98*0.609-1),2))) -> 2.05 | T98: =IF($A98="","",IFERROR(SUM($S$5:S98),0)) -> 128.66
A99: 46199 | B99: Pokerstars | C99: Weiz - Marchfeld Mannsdorf Grossenzersdorf | D99: Hándicap | E99: European Handicap2(-2.0) | F99: 2 | G99: 17 | H99: Normal | I99: Perdida | J99: =IF($A99="","",IF($I99="Ganada",ROUND($G99*($F99-1),2),IF($I99="Medio Ganada",ROUND($G99/2*($F99-1),2),IF($I99="Perdida",IF($H99="Free Bet",0,-$G99),IF($I99="Medio Perdida",IF($H99="Free Bet",0,-$G99/2),IF($I99="Reembolso",IF($R99="","",ROUND($R99-$G99,2)),IF($I99="Anulada",0,""))))))) -> -17 | K99: =IF(J99="","",2000+SUM(J$5:J99)) -> 2349.59 | L99: =IF(OR($I99="Ganada",$I99="Perdida",$I99="Medio Ganada",$I99="Medio Perdida"),IF($G99=0,"",J99/$G99),"") -> -1 | M99: =IF(OR($A99="",$B99=""),"",COUNTIFS($A$5:A99,A99,$B$5:B99,B99)) -> 4 | N99: =IF($A99="","",COUNTA($A$5:$A99)) -> 95 | O99: =IF($A99="","",COUNTA($A$5:$A99)) -> 95 | P99: =IF($K99="","",MAX($K$5:K99)) -> 2366.59 | Q99: =IF($K99="","",K99-P99) -> -17 | S99: =IF(OR($A99="",$F99=""),"",IF($I99="Pendiente","",ROUND($G99*($F99*0.609-1),2))) -> 3.71 | T99: =IF($A99="","",IFERROR(SUM($S$5:S99),0)) -> 132.37
A100: 46199 | B100: Pokerstars | C100: Onsala BK - Landvetter IS | D100: 1X2/ML | E100: 1 | F100: 2.15 | G100: 17 | H100: Normal | I100: Perdida | J100: =IF($A100="","",IF($I100="Ganada",ROUND($G100*($F100-1),2),IF($I100="Medio Ganada",ROUND($G100/2*($F100-1),2),IF($I100="Perdida",IF($H100="Free Bet",0,-$G100),IF($I100="Medio Perdida",IF($H100="Free Bet",0,-$G100/2),IF($I100="Reembolso",IF($R100="","",ROUND($R100-$G100,2)),IF($I100="Anulada",0,""))))))) -> -17 | K100: =IF(J100="","",2000+SUM(J$5:J100)) -> 2332.59 | L100: =IF(OR($I100="Ganada",$I100="Perdida",$I100="Medio Ganada",$I100="Medio Perdida"),IF($G100=0,"",J100/$G100),"") -> -1 | M100: =IF(OR($A100="",$B100=""),"",COUNTIFS($A$5:A100,A100,$B$5:B100,B100)) -> 5 | N100: =IF($A100="","",COUNTA($A$5:$A100)) -> 96 | O100: =IF($A100="","",COUNTA($A$5:$A100)) -> 96 | P100: =IF($K100="","",MAX($K$5:K100)) -> 2366.59 | Q100: =IF($K100="","",K100-P100) -> -34 | S100: =IF(OR($A100="",$F100=""),"",IF($I100="Pendiente","",ROUND($G100*($F100*0.609-1),2))) -> 5.26 | T100: =IF($A100="","",IFERROR(SUM($S$5:S100),0)) -> 137.63
A101: 46199 | B101: GoldenBull | C101: Dundalk - Waterford FC | D101: Totales O/U | E101: Total Under(10.5) - Corners - regular time | F101: 1.93 | G101: 17 | H101: Normal | I101: Ganada | J101: =IF($A101="","",IF($I101="Ganada",ROUND($G101*($F101-1),2),IF($I101="Medio Ganada",ROUND($G101/2*($F101-1),2),IF($I101="Perdida",IF($H101="Free Bet",0,-$G101),IF($I101="Medio Perdida",IF($H101="Free Bet",0,-$G101/2),IF($I101="Reembolso",IF($R101="","",ROUND($R101-$G101,2)),IF($I101="Anulada",0,""))))))) -> 15.81 | K101: =IF(J101="","",2000+SUM(J$5:J101)) -> 2348.4 | L101: =IF(OR($I101="Ganada",$I101="Perdida",$I101="Medio Ganada",$I101="Medio Perdida"),IF($G101=0,"",J101/$G101),"") -> 0.93 | M101: =IF(OR($A101="",$B101=""),"",COUNTIFS($A$5:A101,A101,$B$5:B101,B101)) -> 1 | N101: =IF($A101="","",COUNTA($A$5:$A101)) -> 97 | O101: =IF($A101="","",COUNTA($A$5:$A101)) -> 97 | P101: =IF($K101="","",MAX($K$5:K101)) -> 2366.59 | Q101: =IF($K101="","",K101-P101) -> -18.19 | S101: =IF(OR($A101="",$F101=""),"",IF($I101="Pendiente","",ROUND($G101*($F101*0.609-1),2))) -> 2.98 | T101: =IF($A101="","",IFERROR(SUM($S$5:S101),0)) -> 140.61
A102: 46199 | B102: Winamax | C102: Union La Calera - Santiago Wanderers | D102: Totales O/U | E102: Total Under(1.5) for Team1 - regular time | F102: 1.98 | G102: 17 | H102: Normal | I102: Perdida | J102: =IF($A102="","",IF($I102="Ganada",ROUND($G102*($F102-1),2),IF($I102="Medio Ganada",ROUND($G102/2*($F102-1),2),IF($I102="Perdida",IF($H102="Free Bet",0,-$G102),IF($I102="Medio Perdida",IF($H102="Free Bet",0,-$G102/2),IF($I102="Reembolso",IF($R102="","",ROUND($R102-$G102,2)),IF($I102="Anulada",0,""))))))) -> -17 | K102: =IF(J102="","",2000+SUM(J$5:J102)) -> 2331.4 | L102: =IF(OR($I102="Ganada",$I102="Perdida",$I102="Medio Ganada",$I102="Medio Perdida"),IF($G102=0,"",J102/$G102),"") -> -1 | M102: =IF(OR($A102="",$B102=""),"",COUNTIFS($A$5:A102,A102,$B$5:B102,B102)) -> 3 | N102: =IF($A102="","",COUNTA($A$5:$A102)) -> 98 | O102: =IF($A102="","",COUNTA($A$5:$A102)) -> 98 | P102: =IF($K102="","",MAX($K$5:K102)) -> 2366.59 | Q102: =IF($K102="","",K102-P102) -> -35.19 | S102: =IF(OR($A102="",$F102=""),"",IF($I102="Pendiente","",ROUND($G102*($F102*0.609-1),2))) -> 3.5 | T102: =IF($A102="","",IFERROR(SUM($S$5:S102),0)) -> 144.11
A103: 46199 | B103: Winamax | C103: Audax Rio RJ - Resende RJ [Regular time | D103: DNB | E103: AH2(0.0)/DNB | F103: 1.43 | G103: 28 | H103: Normal | I103: Perdida | J103: =IF($A103="","",IF($I103="Ganada",ROUND($G103*($F103-1),2),IF($I103="Medio Ganada",ROUND($G103/2*($F103-1),2),IF($I103="Perdida",IF($H103="Free Bet",0,-$G103),IF($I103="Medio Perdida",IF($H103="Free Bet",0,-$G103/2),IF($I103="Reembolso",IF($R103="","",ROUND($R103-$G103,2)),IF($I103="Anulada",0,""))))))) -> -28 | K103: =IF(J103="","",2000+SUM(J$5:J103)) -> 2303.4 | L103: =IF(OR($I103="Ganada",$I103="Perdida",$I103="Medio Ganada",$I103="Medio Perdida"),IF($G103=0,"",J103/$G103),"") -> -1 | M103: =IF(OR($A103="",$B103=""),"",COUNTIFS($A$5:A103,A103,$B$5:B103,B103)) -> 4 | N103: =IF($A103="","",COUNTA($A$5:$A103)) -> 99 | O103: =IF($A103="","",COUNTA($A$5:$A103)) -> 99 | P103: =IF($K103="","",MAX($K$5:K103)) -> 2366.59 | Q103: =IF($K103="","",K103-P103) -> -63.19 | S103: =IF(OR($A103="",$F103=""),"",IF($I103="Pendiente","",ROUND($G103*($F103*0.609-1),2))) -> -3.62 | T103: =IF($A103="","",IFERROR(SUM($S$5:S103),0)) -> 140.49
A104: 46199 | B104: Pokerstars | C104: Athlone Town - Finn Harps | D104: Otro | E104: One scoreless | F104: 2.05 | G104: 17 | H104: Normal | I104: Perdida | J104: =IF($A104="","",IF($I104="Ganada",ROUND($G104*($F104-1),2),IF($I104="Medio Ganada",ROUND($G104/2*($F104-1),2),IF($I104="Perdida",IF($H104="Free Bet",0,-$G104),IF($I104="Medio Perdida",IF($H104="Free Bet",0,-$G104/2),IF($I104="Reembolso",IF($R104="","",ROUND($R104-$G104,2)),IF($I104="Anulada",0,""))))))) -> -17 | K104: =IF(J104="","",2000+SUM(J$5:J104)) -> 2286.4 | L104: =IF(OR($I104="Ganada",$I104="Perdida",$I104="Medio Ganada",$I104="Medio Perdida"),IF($G104=0,"",J104/$G104),"") -> -1 | M104: =IF(OR($A104="",$B104=""),"",COUNTIFS($A$5:A104,A104,$B$5:B104,B104)) -> 6 | N104: =IF($A104="","",COUNTA($A$5:$A104)) -> 100 | O104: =IF($A104="","",COUNTA($A$5:$A104)) -> 100 | P104: =IF($K104="","",MAX($K$5:K104)) -> 2366.59 | Q104: =IF($K104="","",K104-P104) -> -80.19 | S104: =IF(OR($A104="",$F104=""),"",IF($I104="Pendiente","",ROUND($G104*($F104*0.609-1),2))) -> 4.22 | T104: =IF($A104="","",IFERROR(SUM($S$5:S104),0)) -> 144.71
A105: 46199 | B105: Winamax | C105: Norway - France | D105: 1X2/ML | E105: 2 | F105: 1.16 | G105: 28 | H105: Normal | I105: Ganada | J105: =IF($A105="","",IF($I105="Ganada",ROUND($G105*($F105-1),2),IF($I105="Medio Ganada",ROUND($G105/2*($F105-1),2),IF($I105="Perdida",IF($H105="Free Bet",0,-$G105),IF($I105="Medio Perdida",IF($H105="Free Bet",0,-$G105/2),IF($I105="Reembolso",IF($R105="","",ROUND($R105-$G105,2)),IF($I105="Anulada",0,""))))))) -> 4.48 | K105: =IF(J105="","",2000+SUM(J$5:J105)) -> 2290.88 | L105: =IF(OR($I105="Ganada",$I105="Perdida",$I105="Medio Ganada",$I105="Medio Perdida"),IF($G105=0,"",J105/$G105),"") -> 0.16 | M105: =IF(OR($A105="",$B105=""),"",COUNTIFS($A$5:A105,A105,$B$5:B105,B105)) -> 5 | N105: =IF($A105="","",COUNTA($A$5:$A105)) -> 101 | O105: =IF($A105="","",COUNTA($A$5:$A105)) -> 101 | P105: =IF($K105="","",MAX($K$5:K105)) -> 2366.59 | Q105: =IF($K105="","",K105-P105) -> -75.71 | S105: =IF(OR($A105="",$F105=""),"",IF($I105="Pendiente","",ROUND($G105*($F105*0.609-1),2))) -> -8.22 | T105: =IF($A105="","",IFERROR(SUM($S$5:S105),0)) -> 136.49
A106: 46199 | B106: Winamax | C106: Lokomotiva Zagreb - NK Varazdin | D106: Hándicap | E106: Asian Handicap1(0) - 1st | F106: 1.9 | G106: 17 | H106: Normal | I106: Ganada | J106: =IF($A106="","",IF($I106="Ganada",ROUND($G106*($F106-1),2),IF($I106="Medio Ganada",ROUND($G106/2*($F106-1),2),IF($I106="Perdida",IF($H106="Free Bet",0,-$G106),IF($I106="Medio Perdida",IF($H106="Free Bet",0,-$G106/2),IF($I106="Reembolso",IF($R106="","",ROUND($R106-$G106,2)),IF($I106="Anulada",0,""))))))) -> 15.3 | K106: =IF(J106="","",2000+SUM(J$5:J106)) -> 2306.18 | L106: =IF(OR($I106="Ganada",$I106="Perdida",$I106="Medio Ganada",$I106="Medio Perdida"),IF($G106=0,"",J106/$G106),"") -> 0.9 | M106: =IF(OR($A106="",$B106=""),"",COUNTIFS($A$5:A106,A106,$B$5:B106,B106)) -> 6 | N106: =IF($A106="","",COUNTA($A$5:$A106)) -> 102 | O106: =IF($A106="","",COUNTA($A$5:$A106)) -> 102 | P106: =IF($K106="","",MAX($K$5:K106)) -> 2366.59 | Q106: =IF($K106="","",K106-P106) -> -60.41 | S106: =IF(OR($A106="",$F106=""),"",IF($I106="Pendiente","",ROUND($G106*($F106*0.609-1),2))) -> 2.67 | T106: =IF($A106="","",IFERROR(SUM($S$5:S106),0)) -> 139.16
A107: 46199 | B107: Winamax | C107: Heidelberg United Women - Boroondara Eagles FC Women | D107: Hándicap | E107: Asian Handicap1(0.25) - 1st | F107: 1.68 | G107: 23 | H107: Normal | I107: Perdida | J107: =IF($A107="","",IF($I107="Ganada",ROUND($G107*($F107-1),2),IF($I107="Medio Ganada",ROUND($G107/2*($F107-1),2),IF($I107="Perdida",IF($H107="Free Bet",0,-$G107),IF($I107="Medio Perdida",IF($H107="Free Bet",0,-$G107/2),IF($I107="Reembolso",IF($R107="","",ROUND($R107-$G107,2)),IF($I107="Anulada",0,""))))))) -> -23 | K107: =IF(J107="","",2000+SUM(J$5:J107)) -> 2283.18 | L107: =IF(OR($I107="Ganada",$I107="Perdida",$I107="Medio Ganada",$I107="Medio Perdida"),IF($G107=0,"",J107/$G107),"") -> -1 | M107: =IF(OR($A107="",$B107=""),"",COUNTIFS($A$5:A107,A107,$B$5:B107,B107)) -> 7 | N107: =IF($A107="","",COUNTA($A$5:$A107)) -> 103 | O107: =IF($A107="","",COUNTA($A$5:$A107)) -> 103 | P107: =IF($K107="","",MAX($K$5:K107)) -> 2366.59 | Q107: =IF($K107="","",K107-P107) -> -83.41 | S107: =IF(OR($A107="",$F107=""),"",IF($I107="Pendiente","",ROUND($G107*($F107*0.609-1),2))) -> 0.53 | T107: =IF($A107="","",IFERROR(SUM($S$5:S107),0)) -> 139.69
A108: 46199 | B108: Pokerstars | C108: Bohemians Dublin - St. Patricks Athletic | D108: Totales O/U | E108: Total Under(2.5) | F108: 1.86 | G108: 17 | H108: Normal | I108: Ganada | J108: =IF($A108="","",IF($I108="Ganada",ROUND($G108*($F108-1),2),IF($I108="Medio Ganada",ROUND($G108/2*($F108-1),2),IF($I108="Perdida",IF($H108="Free Bet",0,-$G108),IF($I108="Medio Perdida",IF($H108="Free Bet",0,-$G108/2),IF($I108="Reembolso",IF($R108="","",ROUND($R108-$G108,2)),IF($I108="Anulada",0,""))))))) -> 14.62 | K108: =IF(J108="","",2000+SUM(J$5:J108)) -> 2297.8 | L108: =IF(OR($I108="Ganada",$I108="Perdida",$I108="Medio Ganada",$I108="Medio Perdida"),IF($G108=0,"",J108/$G108),"") -> 0.86 | M108: =IF(OR($A108="",$B108=""),"",COUNTIFS($A$5:A108,A108,$B$5:B108,B108)) -> 7 | N108: =IF($A108="","",COUNTA($A$5:$A108)) -> 104 | O108: =IF($A108="","",COUNTA($A$5:$A108)) -> 104 | P108: =IF($K108="","",MAX($K$5:K108)) -> 2366.59 | Q108: =IF($K108="","",K108-P108) -> -68.79 | S108: =IF(OR($A108="",$F108=""),"",IF($I108="Pendiente","",ROUND($G108*($F108*0.609-1),2))) -> 2.26 | T108: =IF($A108="","",IFERROR(SUM($S$5:S108),0)) -> 141.95
A109: 46199 | B109: Winamax | C109: NEW VISION – Julie&cie | D109: Hándicap | E109: Hándicap asiático 1 -1.5 mapa | F109: 1.7 | G109: 28 | H109: Normal | I109: Perdida | J109: =IF($A109="","",IF($I109="Ganada",ROUND($G109*($F109-1),2),IF($I109="Medio Ganada",ROUND($G109/2*($F109-1),2),IF($I109="Perdida",IF($H109="Free Bet",0,-$G109),IF($I109="Medio Perdida",IF($H109="Free Bet",0,-$G109/2),IF($I109="Reembolso",IF($R109="","",ROUND($R109-$G109,2)),IF($I109="Anulada",0,""))))))) -> -28 | K109: =IF(J109="","",2000+SUM(J$5:J109)) -> 2269.8 | L109: =IF(OR($I109="Ganada",$I109="Perdida",$I109="Medio Ganada",$I109="Medio Perdida"),IF($G109=0,"",J109/$G109),"") -> -1 | M109: =IF(OR($A109="",$B109=""),"",COUNTIFS($A$5:A109,A109,$B$5:B109,B109)) -> 8 | N109: =IF($A109="","",COUNTA($A$5:$A109)) -> 105 | O109: =IF($A109="","",COUNTA($A$5:$A109)) -> 105 | P109: =IF($K109="","",MAX($K$5:K109)) -> 2366.59 | Q109: =IF($K109="","",K109-P109) -> -96.79 | S109: =IF(OR($A109="",$F109=""),"",IF($I109="Pendiente","",ROUND($G109*($F109*0.609-1),2))) -> 0.99 | T109: =IF($A109="","",IFERROR(SUM($S$5:S109),0)) -> 142.94
A110: 46199 | B110: Winamax | C110: Povazska Bystrica – FC Banik Ostrava B | D110: DNB | E110: 2 | F110: 1.8 | G110: 28 | H110: Normal | I110: Ganada | J110: =IF($A110="","",IF($I110="Ganada",ROUND($G110*($F110-1),2),IF($I110="Medio Ganada",ROUND($G110/2*($F110-1),2),IF($I110="Perdida",IF($H110="Free Bet",0,-$G110),IF($I110="Medio Perdida",IF($H110="Free Bet",0,-$G110/2),IF($I110="Reembolso",IF($R110="","",ROUND($R110-$G110,2)),IF($I110="Anulada",0,""))))))) -> 22.4 | K110: =IF(J110="","",2000+SUM(J$5:J110)) -> 2292.2 | L110: =IF(OR($I110="Ganada",$I110="Perdida",$I110="Medio Ganada",$I110="Medio Perdida"),IF($G110=0,"",J110/$G110),"") -> 0.8 | M110: =IF(OR($A110="",$B110=""),"",COUNTIFS($A$5:A110,A110,$B$5:B110,B110)) -> 9 | N110: =IF($A110="","",COUNTA($A$5:$A110)) -> 106 | O110: =IF($A110="","",COUNTA($A$5:$A110)) -> 106 | P110: =IF($K110="","",MAX($K$5:K110)) -> 2366.59 | Q110: =IF($K110="","",K110-P110) -> -74.39 | S110: =IF(OR($A110="",$F110=""),"",IF($I110="Pendiente","",ROUND($G110*($F110*0.609-1),2))) -> 2.69 | T110: =IF($A110="","",IFERROR(SUM($S$5:S110),0)) -> 145.63
A111: 46200 | B111: GoldenBull | C111: Novorizontino-SP - Vila Nova-GO | D111: Totales O/U | E111: Total Under(1.5) for Team2 - regular time | F111: 1.76 | G111: 23 | H111: Normal | I111: Ganada | J111: =IF($A111="","",IF($I111="Ganada",ROUND($G111*($F111-1),2),IF($I111="Medio Ganada",ROUND($G111/2*($F111-1),2),IF($I111="Perdida",IF($H111="Free Bet",0,-$G111),IF($I111="Medio Perdida",IF($H111="Free Bet",0,-$G111/2),IF($I111="Reembolso",IF($R111="","",ROUND($R111-$G111,2)),IF($I111="Anulada",0,""))))))) -> 17.48 | K111: =IF(J111="","",2000+SUM(J$5:J111)) -> 2309.68 | L111: =IF(OR($I111="Ganada",$I111="Perdida",$I111="Medio Ganada",$I111="Medio Perdida"),IF($G111=0,"",J111/$G111),"") -> 0.76 | M111: =IF(OR($A111="",$B111=""),"",COUNTIFS($A$5:A111,A111,$B$5:B111,B111)) -> 1 | N111: =IF($A111="","",COUNTA($A$5:$A111)) -> 107 | O111: =IF($A111="","",COUNTA($A$5:$A111)) -> 107 | P111: =IF($K111="","",MAX($K$5:K111)) -> 2366.59 | Q111: =IF($K111="","",K111-P111) -> -56.91 | S111: =IF(OR($A111="",$F111=""),"",IF($I111="Pendiente","",ROUND($G111*($F111*0.609-1),2))) -> 1.65 | T111: =IF($A111="","",IFERROR(SUM($S$5:S111),0)) -> 147.28
A112: 46200 | B112: GoldenBull | C112: Chicago Sky (W) - Portland Fire (W | D112: Totales O/U | E112: Total Over(85.5) for Team2 - with OT | F112: 2.07 | G112: 17 | H112: Normal | I112: Ganada | J112: =IF($A112="","",IF($I112="Ganada",ROUND($G112*($F112-1),2),IF($I112="Medio Ganada",ROUND($G112/2*($F112-1),2),IF($I112="Perdida",IF($H112="Free Bet",0,-$G112),IF($I112="Medio Perdida",IF($H112="Free Bet",0,-$G112/2),IF($I112="Reembolso",IF($R112="","",ROUND($R112-$G112,2)),IF($I112="Anulada",0,""))))))) -> 18.19 | K112: =IF(J112="","",2000+SUM(J$5:J112)) -> 2327.87 | L112: =IF(OR($I112="Ganada",$I112="Perdida",$I112="Medio Ganada",$I112="Medio Perdida"),IF($G112=0,"",J112/$G112),"") -> 1.07 | M112: =IF(OR($A112="",$B112=""),"",COUNTIFS($A$5:A112,A112,$B$5:B112,B112)) -> 2 | N112: =IF($A112="","",COUNTA($A$5:$A112)) -> 108 | O112: =IF($A112="","",COUNTA($A$5:$A112)) -> 108 | P112: =IF($K112="","",MAX($K$5:K112)) -> 2366.59 | Q112: =IF($K112="","",K112-P112) -> -38.72 | S112: =IF(OR($A112="",$F112=""),"",IF($I112="Pendiente","",ROUND($G112*($F112*0.609-1),2))) -> 4.43 | T112: =IF($A112="","",IFERROR(SUM($S$5:S112),0)) -> 151.71
A113: 46200 | B113: GoldenBull | C113: Detroit Tigers - Houston Astros | D113: Totales O/U | E113: Total Over(9.5) for Team1 - with OT | F113: 1.85 | G113: 17 | H113: Normal | I113: Perdida | J113: =IF($A113="","",IF($I113="Ganada",ROUND($G113*($F113-1),2),IF($I113="Medio Ganada",ROUND($G113/2*($F113-1),2),IF($I113="Perdida",IF($H113="Free Bet",0,-$G113),IF($I113="Medio Perdida",IF($H113="Free Bet",0,-$G113/2),IF($I113="Reembolso",IF($R113="","",ROUND($R113-$G113,2)),IF($I113="Anulada",0,""))))))) -> -17 | K113: =IF(J113="","",2000+SUM(J$5:J113)) -> 2310.87 | L113: =IF(OR($I113="Ganada",$I113="Perdida",$I113="Medio Ganada",$I113="Medio Perdida"),IF($G113=0,"",J113/$G113),"") -> -1 | M113: =IF(OR($A113="",$B113=""),"",COUNTIFS($A$5:A113,A113,$B$5:B113,B113)) -> 3 | N113: =IF($A113="","",COUNTA($A$5:$A113)) -> 109 | O113: =IF($A113="","",COUNTA($A$5:$A113)) -> 109 | P113: =IF($K113="","",MAX($K$5:K113)) -> 2366.59 | Q113: =IF($K113="","",K113-P113) -> -55.72 | S113: =IF(OR($A113="",$F113=""),"",IF($I113="Pendiente","",ROUND($G113*($F113*0.609-1),2))) -> 2.15 | T113: =IF($A113="","",IFERROR(SUM($S$5:S113),0)) -> 153.86
A114: 46200 | B114: GoldenBull | C114: ga FC Kunoichi (F) - Viamaterasu Miyazaki (F) | D114: Totales O/U | E114: Menos de 0.5 goles | F114: 2.55 | G114: 10 | H114: Free Bet | I114: Ganada | J114: =IF($A114="","",IF($I114="Ganada",ROUND($G114*($F114-1),2),IF($I114="Medio Ganada",ROUND($G114/2*($F114-1),2),IF($I114="Perdida",IF($H114="Free Bet",0,-$G114),IF($I114="Medio Perdida",IF($H114="Free Bet",0,-$G114/2),IF($I114="Reembolso",IF($R114="","",ROUND($R114-$G114,2)),IF($I114="Anulada",0,""))))))) -> 15.5 | K114: =IF(J114="","",2000+SUM(J$5:J114)) -> 2326.37 | L114: =IF(OR($I114="Ganada",$I114="Perdida",$I114="Medio Ganada",$I114="Medio Perdida"),IF($G114=0,"",J114/$G114),"") -> 1.55 | M114: =IF(OR($A114="",$B114=""),"",COUNTIFS($A$5:A114,A114,$B$5:B114,B114)) -> 4 | N114: =IF($A114="","",COUNTA($A$5:$A114)) -> 110 | O114: =IF($A114="","",COUNTA($A$5:$A114)) -> 110 | P114: =IF($K114="","",MAX($K$5:K114)) -> 2366.59 | Q114: =IF($K114="","",K114-P114) -> -40.22 | S114: =IF(OR($A114="",$F114=""),"",IF($I114="Pendiente","",ROUND($G114*($F114*0.609-1),2))) -> 5.53 | T114: =IF($A114="","",IFERROR(SUM($S$5:S114),0)) -> 159.39
A115: 46200 | B115: Yosport | C115: Alana Subasic - Kateryna Lazarenko | D115: 1X2/ML | E115: Team1 Win - regular time | F115: 1.3 | G115: 34 | H115: Normal | I115: Ganada | J115: =IF($A115="","",IF($I115="Ganada",ROUND($G115*($F115-1),2),IF($I115="Medio Ganada",ROUND($G115/2*($F115-1),2),IF($I115="Perdida",IF($H115="Free Bet",0,-$G115),IF($I115="Medio Perdida",IF($H115="Free Bet",0,-$G115/2),IF($I115="Reembolso",IF($R115="","",ROUND($R115-$G115,2)),IF($I115="Anulada",0,""))))))) -> 10.2 | K115: =IF(J115="","",2000+SUM(J$5:J115)) -> 2336.57 | L115: =IF(OR($I115="Ganada",$I115="Perdida",$I115="Medio Ganada",$I115="Medio Perdida"),IF($G115=0,"",J115/$G115),"") -> 0.3 | M115: =IF(OR($A115="",$B115=""),"",COUNTIFS($A$5:A115,A115,$B$5:B115,B115)) -> 1 | N115: =IF($A115="","",COUNTA($A$5:$A115)) -> 111 | O115: =IF($A115="","",COUNTA($A$5:$A115)) -> 111 | P115: =IF($K115="","",MAX($K$5:K115)) -> 2366.59 | Q115: =IF($K115="","",K115-P115) -> -30.02 | S115: =IF(OR($A115="",$F115=""),"",IF($I115="Pendiente","",ROUND($G115*($F115*0.609-1),2))) -> -7.08 | T115: =IF($A115="","",IFERROR(SUM($S$5:S115),0)) -> 152.31
A116: 46200 | B116: Yosport | C116: Beijing Guoan - Wuhan Three Towns | D116: 1X2/ML | E116: 1 | F116: 1.64 | G116: 15 | H116: Normal | I116: Ganada | J116: =IF($A116="","",IF($I116="Ganada",ROUND($G116*($F116-1),2),IF($I116="Medio Ganada",ROUND($G116/2*($F116-1),2),IF($I116="Perdida",IF($H116="Free Bet",0,-$G116),IF($I116="Medio Perdida",IF($H116="Free Bet",0,-$G116/2),IF($I116="Reembolso",IF($R116="","",ROUND($R116-$G116,2)),IF($I116="Anulada",0,""))))))) -> 9.6 | K116: =IF(J116="","",2000+SUM(J$5:J116)) -> 2346.17 | L116: =IF(OR($I116="Ganada",$I116="Perdida",$I116="Medio Ganada",$I116="Medio Perdida"),IF($G116=0,"",J116/$G116),"") -> 0.64 | M116: =IF(OR($A116="",$B116=""),"",COUNTIFS($A$5:A116,A116,$B$5:B116,B116)) -> 2 | N116: =IF($A116="","",COUNTA($A$5:$A116)) -> 112 | O116: =IF($A116="","",COUNTA($A$5:$A116)) -> 112 | P116: =IF($K116="","",MAX($K$5:K116)) -> 2366.59 | Q116: =IF($K116="","",K116-P116) -> -20.42 | S116: =IF(OR($A116="",$F116=""),"",IF($I116="Pendiente","",ROUND($G116*($F116*0.609-1),2))) -> -0.02 | T116: =IF($A116="","",IFERROR(SUM($S$5:S116),0)) -> 152.29
A117: 46200 | B117: SpeedyBet | C117: Ljungskile SK - Örebro SK | D117: Totales O/U | E117: Total Over(8.5) - Corners - regular time | F117: 1.85 | G117: 17 | H117: Normal | I117: Ganada | J117: =IF($A117="","",IF($I117="Ganada",ROUND($G117*($F117-1),2),IF($I117="Medio Ganada",ROUND($G117/2*($F117-1),2),IF($I117="Perdida",IF($H117="Free Bet",0,-$G117),IF($I117="Medio Perdida",IF($H117="Free Bet",0,-$G117/2),IF($I117="Reembolso",IF($R117="","",ROUND($R117-$G117,2)),IF($I117="Anulada",0,""))))))) -> 14.45 | K117: =IF(J117="","",2000+SUM(J$5:J117)) -> 2360.62 | L117: =IF(OR($I117="Ganada",$I117="Perdida",$I117="Medio Ganada",$I117="Medio Perdida"),IF($G117=0,"",J117/$G117),"") -> 0.85 | M117: =IF(OR($A117="",$B117=""),"",COUNTIFS($A$5:A117,A117,$B$5:B117,B117)) -> 1 | N117: =IF($A117="","",COUNTA($A$5:$A117)) -> 113 | O117: =IF($A117="","",COUNTA($A$5:$A117)) -> 113 | P117: =IF($K117="","",MAX($K$5:K117)) -> 2366.59 | Q117: =IF($K117="","",K117-P117) -> -5.97 | S117: =IF(OR($A117="",$F117=""),"",IF($I117="Pendiente","",ROUND($G117*($F117*0.609-1),2))) -> 2.15 | T117: =IF($A117="","",IFERROR(SUM($S$5:S117),0)) -> 154.44
A118: 46200 | B118: SpeedyBet | C118: Zhetysu Taldykorgan - FK Aktobe | D118: Totales O/U | E118: Total Under(0.5) for Team2 - regular time | F118: 2.07 | G118: 17 | H118: Normal | I118: Ganada | J118: =IF($A118="","",IF($I118="Ganada",ROUND($G118*($F118-1),2),IF($I118="Medio Ganada",ROUND($G118/2*($F118-1),2),IF($I118="Perdida",IF($H118="Free Bet",0,-$G118),IF($I118="Medio Perdida",IF($H118="Free Bet",0,-$G118/2),IF($I118="Reembolso",IF($R118="","",ROUND($R118-$G118,2)),IF($I118="Anulada",0,""))))))) -> 18.19 | K118: =IF(J118="","",2000+SUM(J$5:J118)) -> 2378.81 | L118: =IF(OR($I118="Ganada",$I118="Perdida",$I118="Medio Ganada",$I118="Medio Perdida"),IF($G118=0,"",J118/$G118),"") -> 1.07 | M118: =IF(OR($A118="",$B118=""),"",COUNTIFS($A$5:A118,A118,$B$5:B118,B118)) -> 2 | N118: =IF($A118="","",COUNTA($A$5:$A118)) -> 114 | O118: =IF($A118="","",COUNTA($A$5:$A118)) -> 114 | P118: =IF($K118="","",MAX($K$5:K118)) -> 2378.81 | Q118: =IF($K118="","",K118-P118) -> 0 | S118: =IF(OR($A118="",$F118=""),"",IF($I118="Pendiente","",ROUND($G118*($F118*0.609-1),2))) -> 4.43 | T118: =IF($A118="","",IFERROR(SUM($S$5:S118),0)) -> 158.87
A119: 46200 | B119: Paf | C119: HJK Helsinki - KuPS | D119: Hándicap | E119: Asian Handicap2(-0.5) | F119: 1.75 | G119: 5 | H119: Free Bet | I119: Ganada | J119: =IF($A119="","",IF($I119="Ganada",ROUND($G119*($F119-1),2),IF($I119="Medio Ganada",ROUND($G119/2*($F119-1),2),IF($I119="Perdida",IF($H119="Free Bet",0,-$G119),IF($I119="Medio Perdida",IF($H119="Free Bet",0,-$G119/2),IF($I119="Reembolso",IF($R119="","",ROUND($R119-$G119,2)),IF($I119="Anulada",0,""))))))) -> 3.75 | K119: =IF(J119="","",2000+SUM(J$5:J119)) -> 2382.56 | L119: =IF(OR($I119="Ganada",$I119="Perdida",$I119="Medio Ganada",$I119="Medio Perdida"),IF($G119=0,"",J119/$G119),"") -> 0.75 | M119: =IF(OR($A119="",$B119=""),"",COUNTIFS($A$5:A119,A119,$B$5:B119,B119)) -> 1 | N119: =IF($A119="","",COUNTA($A$5:$A119)) -> 115 | O119: =IF($A119="","",COUNTA($A$5:$A119)) -> 115 | P119: =IF($K119="","",MAX($K$5:K119)) -> 2382.56 | Q119: =IF($K119="","",K119-P119) -> 0 | S119: =IF(OR($A119="",$F119=""),"",IF($I119="Pendiente","",ROUND($G119*($F119*0.609-1),2))) -> 0.33 | T119: =IF($A119="","",IFERROR(SUM($S$5:S119),0)) -> 159.2
A120: 46200 | B120: Paf | C120: Inter de Limeira-SP - Maringá-PR | D120: Totales O/U | E120: Total Under(2.5) - regular time | F120: 1.64 | G120: 23 | H120: Normal | I120: Perdida | J120: =IF($A120="","",IF($I120="Ganada",ROUND($G120*($F120-1),2),IF($I120="Medio Ganada",ROUND($G120/2*($F120-1),2),IF($I120="Perdida",IF($H120="Free Bet",0,-$G120),IF($I120="Medio Perdida",IF($H120="Free Bet",0,-$G120/2),IF($I120="Reembolso",IF($R120="","",ROUND($R120-$G120,2)),IF($I120="Anulada",0,""))))))) -> -23 | K120: =IF(J120="","",2000+SUM(J$5:J120)) -> 2359.56 | L120: =IF(OR($I120="Ganada",$I120="Perdida",$I120="Medio Ganada",$I120="Medio Perdida"),IF($G120=0,"",J120/$G120),"") -> -1 | M120: =IF(OR($A120="",$B120=""),"",COUNTIFS($A$5:A120,A120,$B$5:B120,B120)) -> 2 | N120: =IF($A120="","",COUNTA($A$5:$A120)) -> 116 | O120: =IF($A120="","",COUNTA($A$5:$A120)) -> 116 | P120: =IF($K120="","",MAX($K$5:K120)) -> 2382.56 | Q120: =IF($K120="","",K120-P120) -> -23 | S120: =IF(OR($A120="",$F120=""),"",IF($I120="Pendiente","",ROUND($G120*($F120*0.609-1),2))) -> -0.03 | T120: =IF($A120="","",IFERROR(SUM($S$5:S120),0)) -> 159.17
A121: 46200 | B121: SpeedyBet | C121: Haugesund - Kongsvinger | D121: 1X2/ML | E121: 2 | F121: 1.83 | G121: 17 | H121: Normal | I121: Perdida | J121: =IF($A121="","",IF($I121="Ganada",ROUND($G121*($F121-1),2),IF($I121="Medio Ganada",ROUND($G121/2*($F121-1),2),IF($I121="Perdida",IF($H121="Free Bet",0,-$G121),IF($I121="Medio Perdida",IF($H121="Free Bet",0,-$G121/2),IF($I121="Reembolso",IF($R121="","",ROUND($R121-$G121,2)),IF($I121="Anulada",0,""))))))) -> -17 | K121: =IF(J121="","",2000+SUM(J$5:J121)) -> 2342.56 | L121: =IF(OR($I121="Ganada",$I121="Perdida",$I121="Medio Ganada",$I121="Medio Perdida"),IF($G121=0,"",J121/$G121),"") -> -1 | M121: =IF(OR($A121="",$B121=""),"",COUNTIFS($A$5:A121,A121,$B$5:B121,B121)) -> 3 | N121: =IF($A121="","",COUNTA($A$5:$A121)) -> 117 | O121: =IF($A121="","",COUNTA($A$5:$A121)) -> 117 | P121: =IF($K121="","",MAX($K$5:K121)) -> 2382.56 | Q121: =IF($K121="","",K121-P121) -> -40 | S121: =IF(OR($A121="",$F121=""),"",IF($I121="Pendiente","",ROUND($G121*($F121*0.609-1),2))) -> 1.95 | T121: =IF($A121="","",IFERROR(SUM($S$5:S121),0)) -> 161.12
A122: 46200 | B122: Paf | C122: TPS Turku - Jaro | D122: Totales O/U | E122: TPS Turku - Jaro | F122: 1.7 | G122: 22 | H122: Normal | I122: Perdida | J122: =IF($A122="","",IF($I122="Ganada",ROUND($G122*($F122-1),2),IF($I122="Medio Ganada",ROUND($G122/2*($F122-1),2),IF($I122="Perdida",IF($H122="Free Bet",0,-$G122),IF($I122="Medio Perdida",IF($H122="Free Bet",0,-$G122/2),IF($I122="Reembolso",IF($R122="","",ROUND($R122-$G122,2)),IF($I122="Anulada",0,""))))))) -> -22 | K122: =IF(J122="","",2000+SUM(J$5:J122)) -> 2320.56 | L122: =IF(OR($I122="Ganada",$I122="Perdida",$I122="Medio Ganada",$I122="Medio Perdida"),IF($G122=0,"",J122/$G122),"") -> -1 | M122: =IF(OR($A122="",$B122=""),"",COUNTIFS($A$5:A122,A122,$B$5:B122,B122)) -> 3 | N122: =IF($A122="","",COUNTA($A$5:$A122)) -> 118 | O122: =IF($A122="","",COUNTA($A$5:$A122)) -> 118 | P122: =IF($K122="","",MAX($K$5:K122)) -> 2382.56 | Q122: =IF($K122="","",K122-P122) -> -62 | S122: =IF(OR($A122="",$F122=""),"",IF($I122="Pendiente","",ROUND($G122*($F122*0.609-1),2))) -> 0.78 | T122: =IF($A122="","",IFERROR(SUM($S$5:S122),0)) -> 161.9
A123: 46200 | B123: Pokerstars | C123: united ik nordic - Oddevold | D123: Totales O/U | E123: Total Under(6.5) - regular time | F123: 1.44 | G123: 23 | H123: Normal | I123: Ganada | J123: =IF($A123="","",IF($I123="Ganada",ROUND($G123*($F123-1),2),IF($I123="Medio Ganada",ROUND($G123/2*($F123-1),2),IF($I123="Perdida",IF($H123="Free Bet",0,-$G123),IF($I123="Medio Perdida",IF($H123="Free Bet",0,-$G123/2),IF($I123="Reembolso",IF($R123="","",ROUND($R123-$G123,2)),IF($I123="Anulada",0,""))))))) -> 10.12 | K123: =IF(J123="","",2000+SUM(J$5:J123)) -> 2330.68 | L123: =IF(OR($I123="Ganada",$I123="Perdida",$I123="Medio Ganada",$I123="Medio Perdida"),IF($G123=0,"",J123/$G123),"") -> 0.44 | M123: =IF(OR($A123="",$B123=""),"",COUNTIFS($A$5:A123,A123,$B$5:B123,B123)) -> 1 | N123: =IF($A123="","",COUNTA($A$5:$A123)) -> 119 | O123: =IF($A123="","",COUNTA($A$5:$A123)) -> 119 | P123: =IF($K123="","",MAX($K$5:K123)) -> 2382.56 | Q123: =IF($K123="","",K123-P123) -> -51.88 | S123: =IF(OR($A123="",$F123=""),"",IF($I123="Pendiente","",ROUND($G123*($F123*0.609-1),2))) -> -2.83 | T123: =IF($A123="","",IFERROR(SUM($S$5:S123),0)) -> 159.07
A124: 46200 | B124: Pokerstars | C124: spartak varna - Dunav Ruse | D124: Totales O/U | E124: Total Under(0.5) - regular time | F124: 1.5 | G124: 23 | H124: Normal | I124: Ganada | J124: =IF($A124="","",IF($I124="Ganada",ROUND($G124*($F124-1),2),IF($I124="Medio Ganada",ROUND($G124/2*($F124-1),2),IF($I124="Perdida",IF($H124="Free Bet",0,-$G124),IF($I124="Medio Perdida",IF($H124="Free Bet",0,-$G124/2),IF($I124="Reembolso",IF($R124="","",ROUND($R124-$G124,2)),IF($I124="Anulada",0,""))))))) -> 11.5 | K124: =IF(J124="","",2000+SUM(J$5:J124)) -> 2342.18 | L124: =IF(OR($I124="Ganada",$I124="Perdida",$I124="Medio Ganada",$I124="Medio Perdida"),IF($G124=0,"",J124/$G124),"") -> 0.5 | M124: =IF(OR($A124="",$B124=""),"",COUNTIFS($A$5:A124,A124,$B$5:B124,B124)) -> 2 | N124: =IF($A124="","",COUNTA($A$5:$A124)) -> 120 | O124: =IF($A124="","",COUNTA($A$5:$A124)) -> 120 | P124: =IF($K124="","",MAX($K$5:K124)) -> 2382.56 | Q124: =IF($K124="","",K124-P124) -> -40.38 | S124: =IF(OR($A124="",$F124=""),"",IF($I124="Pendiente","",ROUND($G124*($F124*0.609-1),2))) -> -1.99 | T124: =IF($A124="","",IFERROR(SUM($S$5:S124),0)) -> 157.08
A125: 46200 | B125: SpeedyBet | C125: Gnistan - VPS | D125: Totales O/U | E125: Total Under(3.5) - regular time | F125: 1.6 | G125: 23 | H125: Normal | I125: Ganada | J125: =IF($A125="","",IF($I125="Ganada",ROUND($G125*($F125-1),2),IF($I125="Medio Ganada",ROUND($G125/2*($F125-1),2),IF($I125="Perdida",IF($H125="Free Bet",0,-$G125),IF($I125="Medio Perdida",IF($H125="Free Bet",0,-$G125/2),IF($I125="Reembolso",IF($R125="","",ROUND($R125-$G125,2)),IF($I125="Anulada",0,""))))))) -> 13.8 | K125: =IF(J125="","",2000+SUM(J$5:J125)) -> 2355.98 | L125: =IF(OR($I125="Ganada",$I125="Perdida",$I125="Medio Ganada",$I125="Medio Perdida"),IF($G125=0,"",J125/$G125),"") -> 0.6 | M125: =IF(OR($A125="",$B125=""),"",COUNTIFS($A$5:A125,A125,$B$5:B125,B125)) -> 4 | N125: =IF($A125="","",COUNTA($A$5:$A125)) -> 121 | O125: =IF($A125="","",COUNTA($A$5:$A125)) -> 121 | P125: =IF($K125="","",MAX($K$5:K125)) -> 2382.56 | Q125: =IF($K125="","",K125-P125) -> -26.58 | S125: =IF(OR($A125="",$F125=""),"",IF($I125="Pendiente","",ROUND($G125*($F125*0.609-1),2))) -> -0.59 | T125: =IF($A125="","",IFERROR(SUM($S$5:S125),0)) -> 156.49
A126: 46200 | B126: Paf | C126: Gnistan - VPS | D126: Totales O/U | E126: Total Under(8.5) - Corners - regular time | F126: 1.92 | G126: 17 | H126: Normal | I126: Ganada | J126: =IF($A126="","",IF($I126="Ganada",ROUND($G126*($F126-1),2),IF($I126="Medio Ganada",ROUND($G126/2*($F126-1),2),IF($I126="Perdida",IF($H126="Free Bet",0,-$G126),IF($I126="Medio Perdida",IF($H126="Free Bet",0,-$G126/2),IF($I126="Reembolso",IF($R126="","",ROUND($R126-$G126,2)),IF($I126="Anulada",0,""))))))) -> 15.64 | K126: =IF(J126="","",2000+SUM(J$5:J126)) -> 2371.62 | L126: =IF(OR($I126="Ganada",$I126="Perdida",$I126="Medio Ganada",$I126="Medio Perdida"),IF($G126=0,"",J126/$G126),"") -> 0.92 | M126: =IF(OR($A126="",$B126=""),"",COUNTIFS($A$5:A126,A126,$B$5:B126,B126)) -> 4 | N126: =IF($A126="","",COUNTA($A$5:$A126)) -> 122 | O126: =IF($A126="","",COUNTA($A$5:$A126)) -> 122 | P126: =IF($K126="","",MAX($K$5:K126)) -> 2382.56 | Q126: =IF($K126="","",K126-P126) -> -10.94 | S126: =IF(OR($A126="",$F126=""),"",IF($I126="Pendiente","",ROUND($G126*($F126*0.609-1),2))) -> 2.88 | T126: =IF($A126="","",IFERROR(SUM($S$5:S126),0)) -> 159.37
A127: 46200 | B127: SpeedyBet | C127: FC Dila Gori - Torpedo Kutaisi | D127: Totales O/U | E127: Total Over(1.5) | F127: 3 | G127: 5 | H127: Free Bet | I127: Perdida | J127: =IF($A127="","",IF($I127="Ganada",ROUND($G127*($F127-1),2),IF($I127="Medio Ganada",ROUND($G127/2*($F127-1),2),IF($I127="Perdida",IF($H127="Free Bet",0,-$G127),IF($I127="Medio Perdida",IF($H127="Free Bet",0,-$G127/2),IF($I127="Reembolso",IF($R127="","",ROUND($R127-$G127,2)),IF($I127="Anulada",0,""))))))) -> 0 | K127: =IF(J127="","",2000+SUM(J$5:J127)) -> 2371.62 | L127: =IF(OR($I127="Ganada",$I127="Perdida",$I127="Medio Ganada",$I127="Medio Perdida"),IF($G127=0,"",J127/$G127),"") -> 0 | M127: =IF(OR($A127="",$B127=""),"",COUNTIFS($A$5:A127,A127,$B$5:B127,B127)) -> 5 | N127: =IF($A127="","",COUNTA($A$5:$A127)) -> 123 | O127: =IF($A127="","",COUNTA($A$5:$A127)) -> 123 | P127: =IF($K127="","",MAX($K$5:K127)) -> 2382.56 | Q127: =IF($K127="","",K127-P127) -> -10.94 | S127: =IF(OR($A127="",$F127=""),"",IF($I127="Pendiente","",ROUND($G127*($F127*0.609-1),2))) -> 4.14 | T127: =IF($A127="","",IFERROR(SUM($S$5:S127),0)) -> 163.51
A128: 46200 | B128: Paf | C128: Boston Red Sox - New York Yankees | D128: Hándicap | E128: Asian Handicap1(-2.5) | F128: 1.82 | G128: 23 | H128: Normal | I128: Ganada | J128: =IF($A128="","",IF($I128="Ganada",ROUND($G128*($F128-1),2),IF($I128="Medio Ganada",ROUND($G128/2*($F128-1),2),IF($I128="Perdida",IF($H128="Free Bet",0,-$G128),IF($I128="Medio Perdida",IF($H128="Free Bet",0,-$G128/2),IF($I128="Reembolso",IF($R128="","",ROUND($R128-$G128,2)),IF($I128="Anulada",0,""))))))) -> 18.86 | K128: =IF(J128="","",2000+SUM(J$5:J128)) -> 2390.48 | L128: =IF(OR($I128="Ganada",$I128="Perdida",$I128="Medio Ganada",$I128="Medio Perdida"),IF($G128=0,"",J128/$G128),"") -> 0.82 | M128: =IF(OR($A128="",$B128=""),"",COUNTIFS($A$5:A128,A128,$B$5:B128,B128)) -> 5 | N128: =IF($A128="","",COUNTA($A$5:$A128)) -> 124 | O128: =IF($A128="","",COUNTA($A$5:$A128)) -> 124 | P128: =IF($K128="","",MAX($K$5:K128)) -> 2390.48 | Q128: =IF($K128="","",K128-P128) -> 0 | S128: =IF(OR($A128="",$F128=""),"",IF($I128="Pendiente","",ROUND($G128*($F128*0.609-1),2))) -> 2.49 | T128: =IF($A128="","",IFERROR(SUM($S$5:S128),0)) -> 166
A129: 46200 | B129: Paf | C129: Sligo Rovers - Shelbourne | D129: Totales O/U | E129: Total Under(10.5) - Corners - regular time | F129: 1.73 | G129: 21 | H129: Normal | I129: Perdida | J129: =IF($A129="","",IF($I129="Ganada",ROUND($G129*($F129-1),2),IF($I129="Medio Ganada",ROUND($G129/2*($F129-1),2),IF($I129="Perdida",IF($H129="Free Bet",0,-$G129),IF($I129="Medio Perdida",IF($H129="Free Bet",0,-$G129/2),IF($I129="Reembolso",IF($R129="","",ROUND($R129-$G129,2)),IF($I129="Anulada",0,""))))))) -> -21 | K129: =IF(J129="","",2000+SUM(J$5:J129)) -> 2369.48 | L129: =IF(OR($I129="Ganada",$I129="Perdida",$I129="Medio Ganada",$I129="Medio Perdida"),IF($G129=0,"",J129/$G129),"") -> -1 | M129: =IF(OR($A129="",$B129=""),"",COUNTIFS($A$5:A129,A129,$B$5:B129,B129)) -> 6 | N129: =IF($A129="","",COUNTA($A$5:$A129)) -> 125 | O129: =IF($A129="","",COUNTA($A$5:$A129)) -> 125 | P129: =IF($K129="","",MAX($K$5:K129)) -> 2390.48 | Q129: =IF($K129="","",K129-P129) -> -21 | S129: =IF(OR($A129="",$F129=""),"",IF($I129="Pendiente","",ROUND($G129*($F129*0.609-1),2))) -> 1.12 | T129: =IF($A129="","",IFERROR(SUM($S$5:S129),0)) -> 167.12
A130: 46200 | B130: Paf | C130: Slovenia - Italy | D130: 1X2/ML | E130: Team2 Win - with OT | F130: 1.49 | G130: 23 | H130: Normal | I130: Ganada | J130: =IF($A130="","",IF($I130="Ganada",ROUND($G130*($F130-1),2),IF($I130="Medio Ganada",ROUND($G130/2*($F130-1),2),IF($I130="Perdida",IF($H130="Free Bet",0,-$G130),IF($I130="Medio Perdida",IF($H130="Free Bet",0,-$G130/2),IF($I130="Reembolso",IF($R130="","",ROUND($R130-$G130,2)),IF($I130="Anulada",0,""))))))) -> 11.27 | K130: =IF(J130="","",2000+SUM(J$5:J130)) -> 2380.75 | L130: =IF(OR($I130="Ganada",$I130="Perdida",$I130="Medio Ganada",$I130="Medio Perdida"),IF($G130=0,"",J130/$G130),"") -> 0.49 | M130: =IF(OR($A130="",$B130=""),"",COUNTIFS($A$5:A130,A130,$B$5:B130,B130)) -> 7 | N130: =IF($A130="","",COUNTA($A$5:$A130)) -> 126 | O130: =IF($A130="","",COUNTA($A$5:$A130)) -> 126 | P130: =IF($K130="","",MAX($K$5:K130)) -> 2390.48 | Q130: =IF($K130="","",K130-P130) -> -9.73 | S130: =IF(OR($A130="",$F130=""),"",IF($I130="Pendiente","",ROUND($G130*($F130*0.609-1),2))) -> -2.13 | T130: =IF($A130="","",IFERROR(SUM($S$5:S130),0)) -> 164.99
A131: 46200 | B131: Paf | C131: Portuguesa SP - Sampaio Correa RJ | D131: 1X2/ML | E131: 1 | F131: 1.84 | G131: 19 | H131: Normal | I131: Ganada | J131: =IF($A131="","",IF($I131="Ganada",ROUND($G131*($F131-1),2),IF($I131="Medio Ganada",ROUND($G131/2*($F131-1),2),IF($I131="Perdida",IF($H131="Free Bet",0,-$G131),IF($I131="Medio Perdida",IF($H131="Free Bet",0,-$G131/2),IF($I131="Reembolso",IF($R131="","",ROUND($R131-$G131,2)),IF($I131="Anulada",0,""))))))) -> 15.96 | K131: =IF(J131="","",2000+SUM(J$5:J131)) -> 2396.71 | L131: =IF(OR($I131="Ganada",$I131="Perdida",$I131="Medio Ganada",$I131="Medio Perdida"),IF($G131=0,"",J131/$G131),"") -> 0.84 | M131: =IF(OR($A131="",$B131=""),"",COUNTIFS($A$5:A131,A131,$B$5:B131,B131)) -> 8 | N131: =IF($A131="","",COUNTA($A$5:$A131)) -> 127 | O131: =IF($A131="","",COUNTA($A$5:$A131)) -> 127 | P131: =IF($K131="","",MAX($K$5:K131)) -> 2396.71 | Q131: =IF($K131="","",K131-P131) -> 0 | S131: =IF(OR($A131="",$F131=""),"",IF($I131="Pendiente","",ROUND($G131*($F131*0.609-1),2))) -> 2.29 | T131: =IF($A131="","",IFERROR(SUM($S$5:S131),0)) -> 167.28
A132: 46200 | B132: Paf | C132: Sligo Rovers - Shelbourne | D132: 1X2/ML | E132: 1 | F132: 1.4 | G132: 28 | H132: Normal | I132: Perdida | J132: =IF($A132="","",IF($I132="Ganada",ROUND($G132*($F132-1),2),IF($I132="Medio Ganada",ROUND($G132/2*($F132-1),2),IF($I132="Perdida",IF($H132="Free Bet",0,-$G132),IF($I132="Medio Perdida",IF($H132="Free Bet",0,-$G132/2),IF($I132="Reembolso",IF($R132="","",ROUND($R132-$G132,2)),IF($I132="Anulada",0,""))))))) -> -28 | K132: =IF(J132="","",2000+SUM(J$5:J132)) -> 2368.71 | L132: =IF(OR($I132="Ganada",$I132="Perdida",$I132="Medio Ganada",$I132="Medio Perdida"),IF($G132=0,"",J132/$G132),"") -> -1 | M132: =IF(OR($A132="",$B132=""),"",COUNTIFS($A$5:A132,A132,$B$5:B132,B132)) -> 9 | N132: =IF($A132="","",COUNTA($A$5:$A132)) -> 128 | O132: =IF($A132="","",COUNTA($A$5:$A132)) -> 128 | P132: =IF($K132="","",MAX($K$5:K132)) -> 2396.71 | Q132: =IF($K132="","",K132-P132) -> -28 | S132: =IF(OR($A132="",$F132=""),"",IF($I132="Pendiente","",ROUND($G132*($F132*0.609-1),2))) -> -4.13 | T132: =IF($A132="","",IFERROR(SUM($S$5:S132),0)) -> 163.15
A133: 46200 | B133: Paf | C133: Croatia - Ghana | D133: Totales O/U | E133: Total Under(9.5) - Corners - regular time | F133: 1.58 | G133: 23 | H133: Normal | I133: Ganada | J133: =IF($A133="","",IF($I133="Ganada",ROUND($G133*($F133-1),2),IF($I133="Medio Ganada",ROUND($G133/2*($F133-1),2),IF($I133="Perdida",IF($H133="Free Bet",0,-$G133),IF($I133="Medio Perdida",IF($H133="Free Bet",0,-$G133/2),IF($I133="Reembolso",IF($R133="","",ROUND($R133-$G133,2)),IF($I133="Anulada",0,""))))))) -> 13.34 | K133: =IF(J133="","",2000+SUM(J$5:J133)) -> 2382.05 | L133: =IF(OR($I133="Ganada",$I133="Perdida",$I133="Medio Ganada",$I133="Medio Perdida"),IF($G133=0,"",J133/$G133),"") -> 0.58 | M133: =IF(OR($A133="",$B133=""),"",COUNTIFS($A$5:A133,A133,$B$5:B133,B133)) -> 10 | N133: =IF($A133="","",COUNTA($A$5:$A133)) -> 129 | O133: =IF($A133="","",COUNTA($A$5:$A133)) -> 129 | P133: =IF($K133="","",MAX($K$5:K133)) -> 2396.71 | Q133: =IF($K133="","",K133-P133) -> -14.66 | S133: =IF(OR($A133="",$F133=""),"",IF($I133="Pendiente","",ROUND($G133*($F133*0.609-1),2))) -> -0.87 | T133: =IF($A133="","",IFERROR(SUM($S$5:S133),0)) -> 162.28
A134: 46200 | B134: Winamax | C134: Panama - England | D134: 1X2/ML | E134: 2 | F134: 1.17 | G134: 34 | H134: Normal | I134: Ganada | J134: =IF($A134="","",IF($I134="Ganada",ROUND($G134*($F134-1),2),IF($I134="Medio Ganada",ROUND($G134/2*($F134-1),2),IF($I134="Perdida",IF($H134="Free Bet",0,-$G134),IF($I134="Medio Perdida",IF($H134="Free Bet",0,-$G134/2),IF($I134="Reembolso",IF($R134="","",ROUND($R134-$G134,2)),IF($I134="Anulada",0,""))))))) -> 5.78 | K134: =IF(J134="","",2000+SUM(J$5:J134)) -> 2387.83 | L134: =IF(OR($I134="Ganada",$I134="Perdida",$I134="Medio Ganada",$I134="Medio Perdida"),IF($G134=0,"",J134/$G134),"") -> 0.17 | M134: =IF(OR($A134="",$B134=""),"",COUNTIFS($A$5:A134,A134,$B$5:B134,B134)) -> 1 | N134: =IF($A134="","",COUNTA($A$5:$A134)) -> 130 | O134: =IF($A134="","",COUNTA($A$5:$A134)) -> 130 | P134: =IF($K134="","",MAX($K$5:K134)) -> 2396.71 | Q134: =IF($K134="","",K134-P134) -> -8.88 | S134: =IF(OR($A134="",$F134=""),"",IF($I134="Pendiente","",ROUND($G134*($F134*0.609-1),2))) -> -9.77 | T134: =IF($A134="","",IFERROR(SUM($S$5:S134),0)) -> 152.51
A135: 46201 | B135: Pokerstars | C135: SE Gama DF - Mixto MT | D135: Hándicap | E135: European Handicap2(2.0) | F135: 1.91 | G135: 17 | H135: Normal | I135: Ganada | J135: =IF($A135="","",IF($I135="Ganada",ROUND($G135*($F135-1),2),IF($I135="Medio Ganada",ROUND($G135/2*($F135-1),2),IF($I135="Perdida",IF($H135="Free Bet",0,-$G135),IF($I135="Medio Perdida",IF($H135="Free Bet",0,-$G135/2),IF($I135="Reembolso",IF($R135="","",ROUND($R135-$G135,2)),IF($I135="Anulada",0,""))))))) -> 15.47 | K135: =IF(J135="","",2000+SUM(J$5:J135)) -> 2403.3 | L135: =IF(OR($I135="Ganada",$I135="Perdida",$I135="Medio Ganada",$I135="Medio Perdida"),IF($G135=0,"",J135/$G135),"") -> 0.91 | M135: =IF(OR($A135="",$B135=""),"",COUNTIFS($A$5:A135,A135,$B$5:B135,B135)) -> 1 | N135: =IF($A135="","",COUNTA($A$5:$A135)) -> 131 | O135: =IF($A135="","",COUNTA($A$5:$A135)) -> 131 | P135: =IF($K135="","",MAX($K$5:K135)) -> 2403.3 | Q135: =IF($K135="","",K135-P135) -> 0 | S135: =IF(OR($A135="",$F135=""),"",IF($I135="Pendiente","",ROUND($G135*($F135*0.609-1),2))) -> 2.77 | T135: =IF($A135="","",IFERROR(SUM($S$5:S135),0)) -> 155.28
A136: 46201 | B136: Winamax | C136: Colombia - Portugal | D136: Totales O/U | E136: Asian Handicap2(-1.5) - Corners - regular time | F136: 1.82 | G136: 17 | H136: Normal | I136: Perdida | J136: =IF($A136="","",IF($I136="Ganada",ROUND($G136*($F136-1),2),IF($I136="Medio Ganada",ROUND($G136/2*($F136-1),2),IF($I136="Perdida",IF($H136="Free Bet",0,-$G136),IF($I136="Medio Perdida",IF($H136="Free Bet",0,-$G136/2),IF($I136="Reembolso",IF($R136="","",ROUND($R136-$G136,2)),IF($I136="Anulada",0,""))))))) -> -17 | K136: =IF(J136="","",2000+SUM(J$5:J136)) -> 2386.3 | L136: =IF(OR($I136="Ganada",$I136="Perdida",$I136="Medio Ganada",$I136="Medio Perdida"),IF($G136=0,"",J136/$G136),"") -> -1 | M136: =IF(OR($A136="",$B136=""),"",COUNTIFS($A$5:A136,A136,$B$5:B136,B136)) -> 1 | N136: =IF($A136="","",COUNTA($A$5:$A136)) -> 132 | O136: =IF($A136="","",COUNTA($A$5:$A136)) -> 132 | P136: =IF($K136="","",MAX($K$5:K136)) -> 2403.3 | Q136: =IF($K136="","",K136-P136) -> -17 | S136: =IF(OR($A136="",$F136=""),"",IF($I136="Pendiente","",ROUND($G136*($F136*0.609-1),2))) -> 1.84 | T136: =IF($A136="","",IFERROR(SUM($S$5:S136),0)) -> 157.12
A137: 46201 | B137: Pokerstars | C137: atleticos de san german - capitanes de arecibo | D137: Hándicap | E137: Asian Handicap2(5.5) - 1st half | F137: 1.83 | G137: 17 | H137: Normal | I137: Ganada | J137: =IF($A137="","",IF($I137="Ganada",ROUND($G137*($F137-1),2),IF($I137="Medio Ganada",ROUND($G137/2*($F137-1),2),IF($I137="Perdida",IF($H137="Free Bet",0,-$G137),IF($I137="Medio Perdida",IF($H137="Free Bet",0,-$G137/2),IF($I137="Reembolso",IF($R137="","",ROUND($R137-$G137,2)),IF($I137="Anulada",0,""))))))) -> 14.11 | K137: =IF(J137="","",2000+SUM(J$5:J137)) -> 2400.41 | L137: =IF(OR($I137="Ganada",$I137="Perdida",$I137="Medio Ganada",$I137="Medio Perdida"),IF($G137=0,"",J137/$G137),"") -> 0.83 | M137: =IF(OR($A137="",$B137=""),"",COUNTIFS($A$5:A137,A137,$B$5:B137,B137)) -> 2 | N137: =IF($A137="","",COUNTA($A$5:$A137)) -> 133 | O137: =IF($A137="","",COUNTA($A$5:$A137)) -> 133 | P137: =IF($K137="","",MAX($K$5:K137)) -> 2403.3 | Q137: =IF($K137="","",K137-P137) -> -2.89 | S137: =IF(OR($A137="",$F137=""),"",IF($I137="Pendiente","",ROUND($G137*($F137*0.609-1),2))) -> 1.95 | T137: =IF($A137="","",IFERROR(SUM($S$5:S137),0)) -> 159.07
A138: 46201 | B138: GoldenBull | C138: Indiana Fever (W) - Los Angeles Sparks (W) | D138: Totales O/U | E138: Total Over(87.5) for Team2 - with OT | F138: 1.95 | G138: 17 | H138: Normal | I138: Perdida | J138: =IF($A138="","",IF($I138="Ganada",ROUND($G138*($F138-1),2),IF($I138="Medio Ganada",ROUND($G138/2*($F138-1),2),IF($I138="Perdida",IF($H138="Free Bet",0,-$G138),IF($I138="Medio Perdida",IF($H138="Free Bet",0,-$G138/2),IF($I138="Reembolso",IF($R138="","",ROUND($R138-$G138,2)),IF($I138="Anulada",0,""))))))) -> -17 | K138: =IF(J138="","",2000+SUM(J$5:J138)) -> 2383.41 | L138: =IF(OR($I138="Ganada",$I138="Perdida",$I138="Medio Ganada",$I138="Medio Perdida"),IF($G138=0,"",J138/$G138),"") -> -1 | M138: =IF(OR($A138="",$B138=""),"",COUNTIFS($A$5:A138,A138,$B$5:B138,B138)) -> 1 | N138: =IF($A138="","",COUNTA($A$5:$A138)) -> 134 | O138: =IF($A138="","",COUNTA($A$5:$A138)) -> 134 | P138: =IF($K138="","",MAX($K$5:K138)) -> 2403.3 | Q138: =IF($K138="","",K138-P138) -> -19.89 | S138: =IF(OR($A138="",$F138=""),"",IF($I138="Pendiente","",ROUND($G138*($F138*0.609-1),2))) -> 3.19 | T138: =IF($A138="","",IFERROR(SUM($S$5:S138),0)) -> 162.26
A139: 46201 | B139: GoldenBull | C139: Algeria - Austria | D139: Otro | E139: Score (0.0) - 1s | F139: 1.6 | G139: 24 | H139: Normal | I139: Perdida | J139: =IF($A139="","",IF($I139="Ganada",ROUND($G139*($F139-1),2),IF($I139="Medio Ganada",ROUND($G139/2*($F139-1),2),IF($I139="Perdida",IF($H139="Free Bet",0,-$G139),IF($I139="Medio Perdida",IF($H139="Free Bet",0,-$G139/2),IF($I139="Reembolso",IF($R139="","",ROUND($R139-$G139,2)),IF($I139="Anulada",0,""))))))) -> -24 | K139: =IF(J139="","",2000+SUM(J$5:J139)) -> 2359.41 | L139: =IF(OR($I139="Ganada",$I139="Perdida",$I139="Medio Ganada",$I139="Medio Perdida"),IF($G139=0,"",J139/$G139),"") -> -1 | M139: =IF(OR($A139="",$B139=""),"",COUNTIFS($A$5:A139,A139,$B$5:B139,B139)) -> 2 | N139: =IF($A139="","",COUNTA($A$5:$A139)) -> 135 | O139: =IF($A139="","",COUNTA($A$5:$A139)) -> 135 | P139: =IF($K139="","",MAX($K$5:K139)) -> 2403.3 | Q139: =IF($K139="","",K139-P139) -> -43.89 | S139: =IF(OR($A139="",$F139=""),"",IF($I139="Pendiente","",ROUND($G139*($F139*0.609-1),2))) -> -0.61 | T139: =IF($A139="","",IFERROR(SUM($S$5:S139),0)) -> 161.65
A140: 46201 | B140: GoldenBull | C140: Dalian Yingbo - Shanghai Shenhua | D140: Totales O/U | E140: Total Under(5.5) - regular time | F140: 1.61 | G140: 24 | H140: Normal | I140: Ganada | J140: =IF($A140="","",IF($I140="Ganada",ROUND($G140*($F140-1),2),IF($I140="Medio Ganada",ROUND($G140/2*($F140-1),2),IF($I140="Perdida",IF($H140="Free Bet",0,-$G140),IF($I140="Medio Perdida",IF($H140="Free Bet",0,-$G140/2),IF($I140="Reembolso",IF($R140="","",ROUND($R140-$G140,2)),IF($I140="Anulada",0,""))))))) -> 14.64 | K140: =IF(J140="","",2000+SUM(J$5:J140)) -> 2374.05 | L140: =IF(OR($I140="Ganada",$I140="Perdida",$I140="Medio Ganada",$I140="Medio Perdida"),IF($G140=0,"",J140/$G140),"") -> 0.61 | M140: =IF(OR($A140="",$B140=""),"",COUNTIFS($A$5:A140,A140,$B$5:B140,B140)) -> 3 | N140: =IF($A140="","",COUNTA($A$5:$A140)) -> 136 | O140: =IF($A140="","",COUNTA($A$5:$A140)) -> 136 | P140: =IF($K140="","",MAX($K$5:K140)) -> 2403.3 | Q140: =IF($K140="","",K140-P140) -> -29.25 | S140: =IF(OR($A140="",$F140=""),"",IF($I140="Pendiente","",ROUND($G140*($F140*0.609-1),2))) -> -0.47 | T140: =IF($A140="","",IFERROR(SUM($S$5:S140),0)) -> 161.18
A141: 46201 | B141: Winamax | C141: Brodd - Haugesund II | D141: Hándicap | E141: Asian Handicap2(0) - 1st | F141: 1.8 | G141: 18 | H141: Normal | I141: Perdida | J141: =IF($A141="","",IF($I141="Ganada",ROUND($G141*($F141-1),2),IF($I141="Medio Ganada",ROUND($G141/2*($F141-1),2),IF($I141="Perdida",IF($H141="Free Bet",0,-$G141),IF($I141="Medio Perdida",IF($H141="Free Bet",0,-$G141/2),IF($I141="Reembolso",IF($R141="","",ROUND($R141-$G141,2)),IF($I141="Anulada",0,""))))))) -> -18 | K141: =IF(J141="","",2000+SUM(J$5:J141)) -> 2356.05 | L141: =IF(OR($I141="Ganada",$I141="Perdida",$I141="Medio Ganada",$I141="Medio Perdida"),IF($G141=0,"",J141/$G141),"") -> -1 | M141: =IF(OR($A141="",$B141=""),"",COUNTIFS($A$5:A141,A141,$B$5:B141,B141)) -> 2 | N141: =IF($A141="","",COUNTA($A$5:$A141)) -> 137 | O141: =IF($A141="","",COUNTA($A$5:$A141)) -> 137 | P141: =IF($K141="","",MAX($K$5:K141)) -> 2403.3 | Q141: =IF($K141="","",K141-P141) -> -47.25 | S141: =IF(OR($A141="",$F141=""),"",IF($I141="Pendiente","",ROUND($G141*($F141*0.609-1),2))) -> 1.73 | T141: =IF($A141="","",IFERROR(SUM($S$5:S141),0)) -> 162.91
A142: 46201 | B142: Pokerstars | C142: SexyPoxyt - MPS Malmin Palloseura | D142: 1X2/ML | E142: 2 | F142: 2.15 | G142: 18 | H142: Normal | I142: Ganada | J142: =IF($A142="","",IF($I142="Ganada",ROUND($G142*($F142-1),2),IF($I142="Medio Ganada",ROUND($G142/2*($F142-1),2),IF($I142="Perdida",IF($H142="Free Bet",0,-$G142),IF($I142="Medio Perdida",IF($H142="Free Bet",0,-$G142/2),IF($I142="Reembolso",IF($R142="","",ROUND($R142-$G142,2)),IF($I142="Anulada",0,""))))))) -> 20.7 | K142: =IF(J142="","",2000+SUM(J$5:J142)) -> 2376.75 | L142: =IF(OR($I142="Ganada",$I142="Perdida",$I142="Medio Ganada",$I142="Medio Perdida"),IF($G142=0,"",J142/$G142),"") -> 1.15 | M142: =IF(OR($A142="",$B142=""),"",COUNTIFS($A$5:A142,A142,$B$5:B142,B142)) -> 3 | N142: =IF($A142="","",COUNTA($A$5:$A142)) -> 138 | O142: =IF($A142="","",COUNTA($A$5:$A142)) -> 138 | P142: =IF($K142="","",MAX($K$5:K142)) -> 2403.3 | Q142: =IF($K142="","",K142-P142) -> -26.55 | S142: =IF(OR($A142="",$F142=""),"",IF($I142="Pendiente","",ROUND($G142*($F142*0.609-1),2))) -> 5.57 | T142: =IF($A142="","",IFERROR(SUM($S$5:S142),0)) -> 168.48
A143: 46201 | B143: Winamax | C143: Caneros del Este - Metros de Santiago | D143: 1X2/ML | E143: 1 | F143: 1.94 | G143: 18 | H143: Normal | I143: Perdida | J143: =IF($A143="","",IF($I143="Ganada",ROUND($G143*($F143-1),2),IF($I143="Medio Ganada",ROUND($G143/2*($F143-1),2),IF($I143="Perdida",IF($H143="Free Bet",0,-$G143),IF($I143="Medio Perdida",IF($H143="Free Bet",0,-$G143/2),IF($I143="Reembolso",IF($R143="","",ROUND($R143-$G143,2)),IF($I143="Anulada",0,""))))))) -> -18 | K143: =IF(J143="","",2000+SUM(J$5:J143)) -> 2358.75 | L143: =IF(OR($I143="Ganada",$I143="Perdida",$I143="Medio Ganada",$I143="Medio Perdida"),IF($G143=0,"",J143/$G143),"") -> -1 | M143: =IF(OR($A143="",$B143=""),"",COUNTIFS($A$5:A143,A143,$B$5:B143,B143)) -> 3 | N143: =IF($A143="","",COUNTA($A$5:$A143)) -> 139 | O143: =IF($A143="","",COUNTA($A$5:$A143)) -> 139 | P143: =IF($K143="","",MAX($K$5:K143)) -> 2403.3 | Q143: =IF($K143="","",K143-P143) -> -44.55 | S143: =IF(OR($A143="",$F143=""),"",IF($I143="Pendiente","",ROUND($G143*($F143*0.609-1),2))) -> 3.27 | T143: =IF($A143="","",IFERROR(SUM($S$5:S143),0)) -> 171.75
A144: 46201 | B144: Winamax | C144: Vindbjart FK – Stabaek IF 2 | D144: Hándicap | E144: Hándicap asiático 1 -1.5 | F144: 1.86 | G144: 24 | H144: Normal | I144: Perdida | J144: =IF($A144="","",IF($I144="Ganada",ROUND($G144*($F144-1),2),IF($I144="Medio Ganada",ROUND($G144/2*($F144-1),2),IF($I144="Perdida",IF($H144="Free Bet",0,-$G144),IF($I144="Medio Perdida",IF($H144="Free Bet",0,-$G144/2),IF($I144="Reembolso",IF($R144="","",ROUND($R144-$G144,2)),IF($I144="Anulada",0,""))))))) -> -24 | K144: =IF(J144="","",2000+SUM(J$5:J144)) -> 2334.75 | L144: =IF(OR($I144="Ganada",$I144="Perdida",$I144="Medio Ganada",$I144="Medio Perdida"),IF($G144=0,"",J144/$G144),"") -> -1 | M144: =IF(OR($A144="",$B144=""),"",COUNTIFS($A$5:A144,A144,$B$5:B144,B144)) -> 4 | N144: =IF($A144="","",COUNTA($A$5:$A144)) -> 140 | O144: =IF($A144="","",COUNTA($A$5:$A144)) -> 140 | P144: =IF($K144="","",MAX($K$5:K144)) -> 2403.3 | Q144: =IF($K144="","",K144-P144) -> -68.55 | S144: =IF(OR($A144="",$F144=""),"",IF($I144="Pendiente","",ROUND($G144*($F144*0.609-1),2))) -> 3.19 | T144: =IF($A144="","",IFERROR(SUM($S$5:S144),0)) -> 174.94
A145: 46201 | B145: GoldenBull | C145: Stjørdals/Blink - Junkeren | D145: Totales O/U | E145: Total Under(1.5) for Team2 - regular time | F145: 1.88 | G145: 18 | H145: Normal | I145: Ganada | J145: =IF($A145="","",IF($I145="Ganada",ROUND($G145*($F145-1),2),IF($I145="Medio Ganada",ROUND($G145/2*($F145-1),2),IF($I145="Perdida",IF($H145="Free Bet",0,-$G145),IF($I145="Medio Perdida",IF($H145="Free Bet",0,-$G145/2),IF($I145="Reembolso",IF($R145="","",ROUND($R145-$G145,2)),IF($I145="Anulada",0,""))))))) -> 15.84 | K145: =IF(J145="","",2000+SUM(J$5:J145)) -> 2350.59 | L145: =IF(OR($I145="Ganada",$I145="Perdida",$I145="Medio Ganada",$I145="Medio Perdida"),IF($G145=0,"",J145/$G145),"") -> 0.88 | M145: =IF(OR($A145="",$B145=""),"",COUNTIFS($A$5:A145,A145,$B$5:B145,B145)) -> 4 | N145: =IF($A145="","",COUNTA($A$5:$A145)) -> 141 | O145: =IF($A145="","",COUNTA($A$5:$A145)) -> 141 | P145: =IF($K145="","",MAX($K$5:K145)) -> 2403.3 | Q145: =IF($K145="","",K145-P145) -> -52.71 | S145: =IF(OR($A145="",$F145=""),"",IF($I145="Pendiente","",ROUND($G145*($F145*0.609-1),2))) -> 2.61 | T145: =IF($A145="","",IFERROR(SUM($S$5:S145),0)) -> 177.55
A146: 46201 | B146: Pokerstars | C146: Tobol Kostanay - FC Altai Oskemen | D146: Totales O/U | E146: Total Over(3.5) | F146: 2.8 | G146: 12 | H146: Normal | I146: Ganada | J146: =IF($A146="","",IF($I146="Ganada",ROUND($G146*($F146-1),2),IF($I146="Medio Ganada",ROUND($G146/2*($F146-1),2),IF($I146="Perdida",IF($H146="Free Bet",0,-$G146),IF($I146="Medio Perdida",IF($H146="Free Bet",0,-$G146/2),IF($I146="Reembolso",IF($R146="","",ROUND($R146-$G146,2)),IF($I146="Anulada",0,""))))))) -> 21.6 | K146: =IF(J146="","",2000+SUM(J$5:J146)) -> 2372.19 | L146: =IF(OR($I146="Ganada",$I146="Perdida",$I146="Medio Ganada",$I146="Medio Perdida"),IF($G146=0,"",J146/$G146),"") -> 1.8 | M146: =IF(OR($A146="",$B146=""),"",COUNTIFS($A$5:A146,A146,$B$5:B146,B146)) -> 4 | N146: =IF($A146="","",COUNTA($A$5:$A146)) -> 142 | O146: =IF($A146="","",COUNTA($A$5:$A146)) -> 142 | P146: =IF($K146="","",MAX($K$5:K146)) -> 2403.3 | Q146: =IF($K146="","",K146-P146) -> -31.11 | S146: =IF(OR($A146="",$F146=""),"",IF($I146="Pendiente","",ROUND($G146*($F146*0.609-1),2))) -> 8.46 | T146: =IF($A146="","",IFERROR(SUM($S$5:S146),0)) -> 186.01
A147: 46201 | B147: Pokerstars | C147: Aland United Women - HPS Women | D147: 1X2/ML | E147: 1 | F147: 2.1 | G147: 12 | H147: Normal | I147: Perdida | J147: =IF($A147="","",IF($I147="Ganada",ROUND($G147*($F147-1),2),IF($I147="Medio Ganada",ROUND($G147/2*($F147-1),2),IF($I147="Perdida",IF($H147="Free Bet",0,-$G147),IF($I147="Medio Perdida",IF($H147="Free Bet",0,-$G147/2),IF($I147="Reembolso",IF($R147="","",ROUND($R147-$G147,2)),IF($I147="Anulada",0,""))))))) -> -12 | K147: =IF(J147="","",2000+SUM(J$5:J147)) -> 2360.19 | L147: =IF(OR($I147="Ganada",$I147="Perdida",$I147="Medio Ganada",$I147="Medio Perdida"),IF($G147=0,"",J147/$G147),"") -> -1 | M147: =IF(OR($A147="",$B147=""),"",COUNTIFS($A$5:A147,A147,$B$5:B147,B147)) -> 5 | N147: =IF($A147="","",COUNTA($A$5:$A147)) -> 143 | O147: =IF($A147="","",COUNTA($A$5:$A147)) -> 143 | P147: =IF($K147="","",MAX($K$5:K147)) -> 2403.3 | Q147: =IF($K147="","",K147-P147) -> -43.11 | S147: =IF(OR($A147="",$F147=""),"",IF($I147="Pendiente","",ROUND($G147*($F147*0.609-1),2))) -> 3.35 | T147: =IF($A147="","",IFERROR(SUM($S$5:S147),0)) -> 189.36
A148: 46201 | B148: Winamax | C148: Villanueva, Gonzalo - Seyboth Wild, Thiago | D148: Totales O/U | E148: Total Over(17.5) - regular time | F148: 1.66 | G148: 24 | H148: Normal | I148: Perdida | J148: =IF($A148="","",IF($I148="Ganada",ROUND($G148*($F148-1),2),IF($I148="Medio Ganada",ROUND($G148/2*($F148-1),2),IF($I148="Perdida",IF($H148="Free Bet",0,-$G148),IF($I148="Medio Perdida",IF($H148="Free Bet",0,-$G148/2),IF($I148="Reembolso",IF($R148="","",ROUND($R148-$G148,2)),IF($I148="Anulada",0,""))))))) -> -24 | K148: =IF(J148="","",2000+SUM(J$5:J148)) -> 2336.19 | L148: =IF(OR($I148="Ganada",$I148="Perdida",$I148="Medio Ganada",$I148="Medio Perdida"),IF($G148=0,"",J148/$G148),"") -> -1 | M148: =IF(OR($A148="",$B148=""),"",COUNTIFS($A$5:A148,A148,$B$5:B148,B148)) -> 5 | N148: =IF($A148="","",COUNTA($A$5:$A148)) -> 144 | O148: =IF($A148="","",COUNTA($A$5:$A148)) -> 144 | P148: =IF($K148="","",MAX($K$5:K148)) -> 2403.3 | Q148: =IF($K148="","",K148-P148) -> -67.11 | S148: =IF(OR($A148="",$F148=""),"",IF($I148="Pendiente","",ROUND($G148*($F148*0.609-1),2))) -> 0.26 | T148: =IF($A148="","",IFERROR(SUM($S$5:S148),0)) -> 189.62
A149: 46201 | B149: Pokerstars | C149: Follo - Levanger | D149: Totales O/U | E149: Total Over(2.5) | F149: 2.5 | G149: 12 | H149: Normal | I149: Perdida | J149: =IF($A149="","",IF($I149="Ganada",ROUND($G149*($F149-1),2),IF($I149="Medio Ganada",ROUND($G149/2*($F149-1),2),IF($I149="Perdida",IF($H149="Free Bet",0,-$G149),IF($I149="Medio Perdida",IF($H149="Free Bet",0,-$G149/2),IF($I149="Reembolso",IF($R149="","",ROUND($R149-$G149,2)),IF($I149="Anulada",0,""))))))) -> -12 | K149: =IF(J149="","",2000+SUM(J$5:J149)) -> 2324.19 | L149: =IF(OR($I149="Ganada",$I149="Perdida",$I149="Medio Ganada",$I149="Medio Perdida"),IF($G149=0,"",J149/$G149),"") -> -1 | M149: =IF(OR($A149="",$B149=""),"",COUNTIFS($A$5:A149,A149,$B$5:B149,B149)) -> 6 | N149: =IF($A149="","",COUNTA($A$5:$A149)) -> 145 | O149: =IF($A149="","",COUNTA($A$5:$A149)) -> 145 | P149: =IF($K149="","",MAX($K$5:K149)) -> 2403.3 | Q149: =IF($K149="","",K149-P149) -> -79.11 | S149: =IF(OR($A149="",$F149=""),"",IF($I149="Pendiente","",ROUND($G149*($F149*0.609-1),2))) -> 6.27 | T149: =IF($A149="","",IFERROR(SUM($S$5:S149),0)) -> 195.89
A150: 46201 | B150: Pokerstars | C150: Kfum 2 - Heming | D150: Totales O/U | E150: Total Over(4.5) | F150: 2.9 | G150: 12 | H150: Normal | I150: Perdida | J150: =IF($A150="","",IF($I150="Ganada",ROUND($G150*($F150-1),2),IF($I150="Medio Ganada",ROUND($G150/2*($F150-1),2),IF($I150="Perdida",IF($H150="Free Bet",0,-$G150),IF($I150="Medio Perdida",IF($H150="Free Bet",0,-$G150/2),IF($I150="Reembolso",IF($R150="","",ROUND($R150-$G150,2)),IF($I150="Anulada",0,""))))))) -> -12 | K150: =IF(J150="","",2000+SUM(J$5:J150)) -> 2312.19 | L150: =IF(OR($I150="Ganada",$I150="Perdida",$I150="Medio Ganada",$I150="Medio Perdida"),IF($G150=0,"",J150/$G150),"") -> -1 | M150: =IF(OR($A150="",$B150=""),"",COUNTIFS($A$5:A150,A150,$B$5:B150,B150)) -> 7 | N150: =IF($A150="","",COUNTA($A$5:$A150)) -> 146 | O150: =IF($A150="","",COUNTA($A$5:$A150)) -> 146 | P150: =IF($K150="","",MAX($K$5:K150)) -> 2403.3 | Q150: =IF($K150="","",K150-P150) -> -91.11 | S150: =IF(OR($A150="",$F150=""),"",IF($I150="Pendiente","",ROUND($G150*($F150*0.609-1),2))) -> 9.19 | T150: =IF($A150="","",IFERROR(SUM($S$5:S150),0)) -> 205.08
A151: 46201 | B151: Winamax | C151: Guapore RO – Monte Roraima RR | D151: Totales O/U | E151: Menos de 3 | F151: 1.6 | G151: 24 | H151: Normal | I151: Ganada | J151: =IF($A151="","",IF($I151="Ganada",ROUND($G151*($F151-1),2),IF($I151="Medio Ganada",ROUND($G151/2*($F151-1),2),IF($I151="Perdida",IF($H151="Free Bet",0,-$G151),IF($I151="Medio Perdida",IF($H151="Free Bet",0,-$G151/2),IF($I151="Reembolso",IF($R151="","",ROUND($R151-$G151,2)),IF($I151="Anulada",0,""))))))) -> 14.4 | K151: =IF(J151="","",2000+SUM(J$5:J151)) -> 2326.59 | L151: =IF(OR($I151="Ganada",$I151="Perdida",$I151="Medio Ganada",$I151="Medio Perdida"),IF($G151=0,"",J151/$G151),"") -> 0.6 | M151: =IF(OR($A151="",$B151=""),"",COUNTIFS($A$5:A151,A151,$B$5:B151,B151)) -> 6 | N151: =IF($A151="","",COUNTA($A$5:$A151)) -> 147 | O151: =IF($A151="","",COUNTA($A$5:$A151)) -> 147 | P151: =IF($K151="","",MAX($K$5:K151)) -> 2403.3 | Q151: =IF($K151="","",K151-P151) -> -76.71 | S151: =IF(OR($A151="",$F151=""),"",IF($I151="Pendiente","",ROUND($G151*($F151*0.609-1),2))) -> -0.61 | T151: =IF($A151="","",IFERROR(SUM($S$5:S151),0)) -> 204.47
A152: 46201 | B152: Pokerstars | C152: KFUM Oslo Fotball II - Heming | D152: Totales O/U | E152: Total Over(3.5) - regular tim | F152: 2.15 | G152: 24 | H152: Normal | I152: Ganada | J152: =IF($A152="","",IF($I152="Ganada",ROUND($G152*($F152-1),2),IF($I152="Medio Ganada",ROUND($G152/2*($F152-1),2),IF($I152="Perdida",IF($H152="Free Bet",0,-$G152),IF($I152="Medio Perdida",IF($H152="Free Bet",0,-$G152/2),IF($I152="Reembolso",IF($R152="","",ROUND($R152-$G152,2)),IF($I152="Anulada",0,""))))))) -> 27.6 | K152: =IF(J152="","",2000+SUM(J$5:J152)) -> 2354.19 | L152: =IF(OR($I152="Ganada",$I152="Perdida",$I152="Medio Ganada",$I152="Medio Perdida"),IF($G152=0,"",J152/$G152),"") -> 1.15 | M152: =IF(OR($A152="",$B152=""),"",COUNTIFS($A$5:A152,A152,$B$5:B152,B152)) -> 8 | N152: =IF($A152="","",COUNTA($A$5:$A152)) -> 148 | O152: =IF($A152="","",COUNTA($A$5:$A152)) -> 148 | P152: =IF($K152="","",MAX($K$5:K152)) -> 2403.3 | Q152: =IF($K152="","",K152-P152) -> -49.11 | S152: =IF(OR($A152="",$F152=""),"",IF($I152="Pendiente","",ROUND($G152*($F152*0.609-1),2))) -> 7.42 | T152: =IF($A152="","",IFERROR(SUM($S$5:S152),0)) -> 211.89
A153: 46201 | B153: GoldenBull | C153: Varhaug - Odds BK 2 | D153: 1X2/ML | E153: 2 | F153: 2.53 | G153: 10 | H153: Normal | I153: Perdida | J153: =IF($A153="","",IF($I153="Ganada",ROUND($G153*($F153-1),2),IF($I153="Medio Ganada",ROUND($G153/2*($F153-1),2),IF($I153="Perdida",IF($H153="Free Bet",0,-$G153),IF($I153="Medio Perdida",IF($H153="Free Bet",0,-$G153/2),IF($I153="Reembolso",IF($R153="","",ROUND($R153-$G153,2)),IF($I153="Anulada",0,""))))))) -> -10 | K153: =IF(J153="","",2000+SUM(J$5:J153)) -> 2344.19 | L153: =IF(OR($I153="Ganada",$I153="Perdida",$I153="Medio Ganada",$I153="Medio Perdida"),IF($G153=0,"",J153/$G153),"") -> -1 | M153: =IF(OR($A153="",$B153=""),"",COUNTIFS($A$5:A153,A153,$B$5:B153,B153)) -> 5 | N153: =IF($A153="","",COUNTA($A$5:$A153)) -> 149 | O153: =IF($A153="","",COUNTA($A$5:$A153)) -> 149 | P153: =IF($K153="","",MAX($K$5:K153)) -> 2403.3 | Q153: =IF($K153="","",K153-P153) -> -59.11 | S153: =IF(OR($A153="",$F153=""),"",IF($I153="Pendiente","",ROUND($G153*($F153*0.609-1),2))) -> 5.41 | T153: =IF($A153="","",IFERROR(SUM($S$5:S153),0)) -> 217.3
A154: 46201 | B154: GoldenBull | C154: UAI Urquiza - Sportivo Italiano | D154: Totales O/U | E154: Total Under(0.5) for Team2 - regular time | F154: 2.1 | G154: 22 | H154: Normal | I154: Ganada | J154: =IF($A154="","",IF($I154="Ganada",ROUND($G154*($F154-1),2),IF($I154="Medio Ganada",ROUND($G154/2*($F154-1),2),IF($I154="Perdida",IF($H154="Free Bet",0,-$G154),IF($I154="Medio Perdida",IF($H154="Free Bet",0,-$G154/2),IF($I154="Reembolso",IF($R154="","",ROUND($R154-$G154,2)),IF($I154="Anulada",0,""))))))) -> 24.2 | K154: =IF(J154="","",2000+SUM(J$5:J154)) -> 2368.39 | L154: =IF(OR($I154="Ganada",$I154="Perdida",$I154="Medio Ganada",$I154="Medio Perdida"),IF($G154=0,"",J154/$G154),"") -> 1.1 | M154: =IF(OR($A154="",$B154=""),"",COUNTIFS($A$5:A154,A154,$B$5:B154,B154)) -> 6 | N154: =IF($A154="","",COUNTA($A$5:$A154)) -> 150 | O154: =IF($A154="","",COUNTA($A$5:$A154)) -> 150 | P154: =IF($K154="","",MAX($K$5:K154)) -> 2403.3 | Q154: =IF($K154="","",K154-P154) -> -34.91 | S154: =IF(OR($A154="",$F154=""),"",IF($I154="Pendiente","",ROUND($G154*($F154*0.609-1),2))) -> 6.14 | T154: =IF($A154="","",IFERROR(SUM($S$5:S154),0)) -> 223.44
A155: 46201 | B155: Paf | C155: Náutico-PE - Goiás-GO | D155: Totales O/U | E155: Total Under(11.5) - Corners - regular time | F155: 1.62 | G155: 23 | H155: Normal | I155: Ganada | J155: =IF($A155="","",IF($I155="Ganada",ROUND($G155*($F155-1),2),IF($I155="Medio Ganada",ROUND($G155/2*($F155-1),2),IF($I155="Perdida",IF($H155="Free Bet",0,-$G155),IF($I155="Medio Perdida",IF($H155="Free Bet",0,-$G155/2),IF($I155="Reembolso",IF($R155="","",ROUND($R155-$G155,2)),IF($I155="Anulada",0,""))))))) -> 14.26 | K155: =IF(J155="","",2000+SUM(J$5:J155)) -> 2382.65 | L155: =IF(OR($I155="Ganada",$I155="Perdida",$I155="Medio Ganada",$I155="Medio Perdida"),IF($G155=0,"",J155/$G155),"") -> 0.62 | M155: =IF(OR($A155="",$B155=""),"",COUNTIFS($A$5:A155,A155,$B$5:B155,B155)) -> 1 | N155: =IF($A155="","",COUNTA($A$5:$A155)) -> 151 | O155: =IF($A155="","",COUNTA($A$5:$A155)) -> 151 | P155: =IF($K155="","",MAX($K$5:K155)) -> 2403.3 | Q155: =IF($K155="","",K155-P155) -> -20.65 | S155: =IF(OR($A155="",$F155=""),"",IF($I155="Pendiente","",ROUND($G155*($F155*0.609-1),2))) -> -0.31 | T155: =IF($A155="","",IFERROR(SUM($S$5:S155),0)) -> 223.13
A156: 46202 | B156: SpeedyBet | C156: Brooklyn City FC (W) - Force FC New York (W) | D156: Totales O/U | E156: Total Under(2.5) - regular time | F156: 2.4 | G156: 11 | H156: Normal | I156: Ganada | J156: =IF($A156="","",IF($I156="Ganada",ROUND($G156*($F156-1),2),IF($I156="Medio Ganada",ROUND($G156/2*($F156-1),2),IF($I156="Perdida",IF($H156="Free Bet",0,-$G156),IF($I156="Medio Perdida",IF($H156="Free Bet",0,-$G156/2),IF($I156="Reembolso",IF($R156="","",ROUND($R156-$G156,2)),IF($I156="Anulada",0,""))))))) -> 15.4 | K156: =IF(J156="","",2000+SUM(J$5:J156)) -> 2398.05 | L156: =IF(OR($I156="Ganada",$I156="Perdida",$I156="Medio Ganada",$I156="Medio Perdida"),IF($G156=0,"",J156/$G156),"") -> 1.4 | M156: =IF(OR($A156="",$B156=""),"",COUNTIFS($A$5:A156,A156,$B$5:B156,B156)) -> 1 | N156: =IF($A156="","",COUNTA($A$5:$A156)) -> 152 | O156: =IF($A156="","",COUNTA($A$5:$A156)) -> 152 | P156: =IF($K156="","",MAX($K$5:K156)) -> 2403.3 | Q156: =IF($K156="","",K156-P156) -> -5.25 | S156: =IF(OR($A156="",$F156=""),"",IF($I156="Pendiente","",ROUND($G156*($F156*0.609-1),2))) -> 5.08 | T156: =IF($A156="","",IFERROR(SUM($S$5:S156),0)) -> 228.21
A157: 46202 | B157: SpeedyBet | C157: Confianca | D157: 1X2/ML | E157: 2 | F157: 2.07 | G157: 23 | H157: Normal | I157: Perdida | J157: =IF($A157="","",IF($I157="Ganada",ROUND($G157*($F157-1),2),IF($I157="Medio Ganada",ROUND($G157/2*($F157-1),2),IF($I157="Perdida",IF($H157="Free Bet",0,-$G157),IF($I157="Medio Perdida",IF($H157="Free Bet",0,-$G157/2),IF($I157="Reembolso",IF($R157="","",ROUND($R157-$G157,2)),IF($I157="Anulada",0,""))))))) -> -23 | K157: =IF(J157="","",2000+SUM(J$5:J157)) -> 2375.05 | L157: =IF(OR($I157="Ganada",$I157="Perdida",$I157="Medio Ganada",$I157="Medio Perdida"),IF($G157=0,"",J157/$G157),"") -> -1 | M157: =IF(OR($A157="",$B157=""),"",COUNTIFS($A$5:A157,A157,$B$5:B157,B157)) -> 2 | N157: =IF($A157="","",COUNTA($A$5:$A157)) -> 153 | O157: =IF($A157="","",COUNTA($A$5:$A157)) -> 153 | P157: =IF($K157="","",MAX($K$5:K157)) -> 2403.3 | Q157: =IF($K157="","",K157-P157) -> -28.25 | S157: =IF(OR($A157="",$F157=""),"",IF($I157="Pendiente","",ROUND($G157*($F157*0.609-1),2))) -> 5.99 | T157: =IF($A157="","",IFERROR(SUM($S$5:S157),0)) -> 234.2
A158: 46202 | B158: Sportium | C158: Fenty, Andrew - Imamura, Masamichi | D158: Hándicap | E158: Asian Handicap1(-3.5) - regular time | F158: 1.7 | G158: 23 | H158: Normal | I158: Ganada | J158: =IF($A158="","",IF($I158="Ganada",ROUND($G158*($F158-1),2),IF($I158="Medio Ganada",ROUND($G158/2*($F158-1),2),IF($I158="Perdida",IF($H158="Free Bet",0,-$G158),IF($I158="Medio Perdida",IF($H158="Free Bet",0,-$G158/2),IF($I158="Reembolso",IF($R158="","",ROUND($R158-$G158,2)),IF($I158="Anulada",0,""))))))) -> 16.1 | K158: =IF(J158="","",2000+SUM(J$5:J158)) -> 2391.15 | L158: =IF(OR($I158="Ganada",$I158="Perdida",$I158="Medio Ganada",$I158="Medio Perdida"),IF($G158=0,"",J158/$G158),"") -> 0.7 | M158: =IF(OR($A158="",$B158=""),"",COUNTIFS($A$5:A158,A158,$B$5:B158,B158)) -> 1 | N158: =IF($A158="","",COUNTA($A$5:$A158)) -> 154 | O158: =IF($A158="","",COUNTA($A$5:$A158)) -> 154 | P158: =IF($K158="","",MAX($K$5:K158)) -> 2403.3 | Q158: =IF($K158="","",K158-P158) -> -12.15 | S158: =IF(OR($A158="",$F158=""),"",IF($I158="Pendiente","",ROUND($G158*($F158*0.609-1),2))) -> 0.81 | T158: =IF($A158="","",IFERROR(SUM($S$5:S158),0)) -> 235.01
A159: 46202 | B159: Sportium | C159: Cilic, Marin - Medvedev, Daniil | D159: Hándicap | E159: Asian Handicap1(6.5) - regular time | F159: 1.727 | G159: 23 | H159: Normal | I159: Perdida | J159: =IF($A159="","",IF($I159="Ganada",ROUND($G159*($F159-1),2),IF($I159="Medio Ganada",ROUND($G159/2*($F159-1),2),IF($I159="Perdida",IF($H159="Free Bet",0,-$G159),IF($I159="Medio Perdida",IF($H159="Free Bet",0,-$G159/2),IF($I159="Reembolso",IF($R159="","",ROUND($R159-$G159,2)),IF($I159="Anulada",0,""))))))) -> -23 | K159: =IF(J159="","",2000+SUM(J$5:J159)) -> 2368.15 | L159: =IF(OR($I159="Ganada",$I159="Perdida",$I159="Medio Ganada",$I159="Medio Perdida"),IF($G159=0,"",J159/$G159),"") -> -1 | M159: =IF(OR($A159="",$B159=""),"",COUNTIFS($A$5:A159,A159,$B$5:B159,B159)) -> 2 | N159: =IF($A159="","",COUNTA($A$5:$A159)) -> 155 | O159: =IF($A159="","",COUNTA($A$5:$A159)) -> 155 | P159: =IF($K159="","",MAX($K$5:K159)) -> 2403.3 | Q159: =IF($K159="","",K159-P159) -> -35.15 | S159: =IF(OR($A159="",$F159=""),"",IF($I159="Pendiente","",ROUND($G159*($F159*0.609-1),2))) -> 1.19 | T159: =IF($A159="","",IFERROR(SUM($S$5:S159),0)) -> 236.2
A160: 46202 | B160: Paf | C160: Leylah Annie Fernandez - Janice Tjen | D160: 1X2/ML | E160: Team1Win - 1 set, 08 game | F160: 1.36 | G160: 36 | H160: Normal | I160: Perdida | J160: =IF($A160="","",IF($I160="Ganada",ROUND($G160*($F160-1),2),IF($I160="Medio Ganada",ROUND($G160/2*($F160-1),2),IF($I160="Perdida",IF($H160="Free Bet",0,-$G160),IF($I160="Medio Perdida",IF($H160="Free Bet",0,-$G160/2),IF($I160="Reembolso",IF($R160="","",ROUND($R160-$G160,2)),IF($I160="Anulada",0,""))))))) -> -36 | K160: =IF(J160="","",2000+SUM(J$5:J160)) -> 2332.15 | L160: =IF(OR($I160="Ganada",$I160="Perdida",$I160="Medio Ganada",$I160="Medio Perdida"),IF($G160=0,"",J160/$G160),"") -> -1 | M160: =IF(OR($A160="",$B160=""),"",COUNTIFS($A$5:A160,A160,$B$5:B160,B160)) -> 1 | N160: =IF($A160="","",COUNTA($A$5:$A160)) -> 156 | O160: =IF($A160="","",COUNTA($A$5:$A160)) -> 156 | P160: =IF($K160="","",MAX($K$5:K160)) -> 2403.3 | Q160: =IF($K160="","",K160-P160) -> -71.15 | S160: =IF(OR($A160="",$F160=""),"",IF($I160="Pendiente","",ROUND($G160*($F160*0.609-1),2))) -> -6.18 | T160: =IF($A160="","",IFERROR(SUM($S$5:S160),0)) -> 230.02
A161: 46202 | B161: Pokerstars | C161: Auda - Riga FC | D161: Totales O/U | E161: Total Over(2.5) | F161: 2.4 | G161: 12 | H161: Normal | I161: Perdida | J161: =IF($A161="","",IF($I161="Ganada",ROUND($G161*($F161-1),2),IF($I161="Medio Ganada",ROUND($G161/2*($F161-1),2),IF($I161="Perdida",IF($H161="Free Bet",0,-$G161),IF($I161="Medio Perdida",IF($H161="Free Bet",0,-$G161/2),IF($I161="Reembolso",IF($R161="","",ROUND($R161-$G161,2)),IF($I161="Anulada",0,""))))))) -> -12 | K161: =IF(J161="","",2000+SUM(J$5:J161)) -> 2320.15 | L161: =IF(OR($I161="Ganada",$I161="Perdida",$I161="Medio Ganada",$I161="Medio Perdida"),IF($G161=0,"",J161/$G161),"") -> -1 | M161: =IF(OR($A161="",$B161=""),"",COUNTIFS($A$5:A161,A161,$B$5:B161,B161)) -> 1 | N161: =IF($A161="","",COUNTA($A$5:$A161)) -> 157 | O161: =IF($A161="","",COUNTA($A$5:$A161)) -> 157 | P161: =IF($K161="","",MAX($K$5:K161)) -> 2403.3 | Q161: =IF($K161="","",K161-P161) -> -83.15 | S161: =IF(OR($A161="",$F161=""),"",IF($I161="Pendiente","",ROUND($G161*($F161*0.609-1),2))) -> 5.54 | T161: =IF($A161="","",IFERROR(SUM($S$5:S161),0)) -> 235.56
A162: 46202 | B162: Paf | C162: Marin Cilic - Daniil Medvedev | D162: Totales O/U | E162: Total Over(12.5) - 3rd | F162: 2.12 | G162: 18 | H162: Normal | I162: Perdida | J162: =IF($A162="","",IF($I162="Ganada",ROUND($G162*($F162-1),2),IF($I162="Medio Ganada",ROUND($G162/2*($F162-1),2),IF($I162="Perdida",IF($H162="Free Bet",0,-$G162),IF($I162="Medio Perdida",IF($H162="Free Bet",0,-$G162/2),IF($I162="Reembolso",IF($R162="","",ROUND($R162-$G162,2)),IF($I162="Anulada",0,""))))))) -> -18 | K162: =IF(J162="","",2000+SUM(J$5:J162)) -> 2302.15 | L162: =IF(OR($I162="Ganada",$I162="Perdida",$I162="Medio Ganada",$I162="Medio Perdida"),IF($G162=0,"",J162/$G162),"") -> -1 | M162: =IF(OR($A162="",$B162=""),"",COUNTIFS($A$5:A162,A162,$B$5:B162,B162)) -> 2 | N162: =IF($A162="","",COUNTA($A$5:$A162)) -> 158 | O162: =IF($A162="","",COUNTA($A$5:$A162)) -> 158 | P162: =IF($K162="","",MAX($K$5:K162)) -> 2403.3 | Q162: =IF($K162="","",K162-P162) -> -101.15 | S162: =IF(OR($A162="",$F162=""),"",IF($I162="Pendiente","",ROUND($G162*($F162*0.609-1),2))) -> 5.24 | T162: =IF($A162="","",IFERROR(SUM($S$5:S162),0)) -> 240.8
A163: 46202 | B163: Sportium | C163: catar -arabia saudi | D163: Hándicap | E163: over6,5 team 1 | F163: 1.9 | G163: 18 | H163: Normal | I163: Ganada | J163: =IF($A163="","",IF($I163="Ganada",ROUND($G163*($F163-1),2),IF($I163="Medio Ganada",ROUND($G163/2*($F163-1),2),IF($I163="Perdida",IF($H163="Free Bet",0,-$G163),IF($I163="Medio Perdida",IF($H163="Free Bet",0,-$G163/2),IF($I163="Reembolso",IF($R163="","",ROUND($R163-$G163,2)),IF($I163="Anulada",0,""))))))) -> 16.2 | K163: =IF(J163="","",2000+SUM(J$5:J163)) -> 2318.35 | L163: =IF(OR($I163="Ganada",$I163="Perdida",$I163="Medio Ganada",$I163="Medio Perdida"),IF($G163=0,"",J163/$G163),"") -> 0.9 | M163: =IF(OR($A163="",$B163=""),"",COUNTIFS($A$5:A163,A163,$B$5:B163,B163)) -> 3 | N163: =IF($A163="","",COUNTA($A$5:$A163)) -> 159 | O163: =IF($A163="","",COUNTA($A$5:$A163)) -> 159 | P163: =IF($K163="","",MAX($K$5:K163)) -> 2403.3 | Q163: =IF($K163="","",K163-P163) -> -84.95 | S163: =IF(OR($A163="",$F163=""),"",IF($I163="Pendiente","",ROUND($G163*($F163*0.609-1),2))) -> 2.83 | T163: =IF($A163="","",IFERROR(SUM($S$5:S163),0)) -> 243.63
A164: 46202 | B164: Sportium | C164: Oleksandra Oliynykova (CRO) v Mccartney Kessler (USA) | D164: 1X2/ML | E164: 2 Ganador v (Set 2, Juego 6) | F164: 1.727 | G164: 22 | H164: Normal | I164: Ganada | J164: =IF($A164="","",IF($I164="Ganada",ROUND($G164*($F164-1),2),IF($I164="Medio Ganada",ROUND($G164/2*($F164-1),2),IF($I164="Perdida",IF($H164="Free Bet",0,-$G164),IF($I164="Medio Perdida",IF($H164="Free Bet",0,-$G164/2),IF($I164="Reembolso",IF($R164="","",ROUND($R164-$G164,2)),IF($I164="Anulada",0,""))))))) -> 15.99 | K164: =IF(J164="","",2000+SUM(J$5:J164)) -> 2334.34 | L164: =IF(OR($I164="Ganada",$I164="Perdida",$I164="Medio Ganada",$I164="Medio Perdida"),IF($G164=0,"",J164/$G164),"") -> 0.72681818 | M164: =IF(OR($A164="",$B164=""),"",COUNTIFS($A$5:A164,A164,$B$5:B164,B164)) -> 4 | N164: =IF($A164="","",COUNTA($A$5:$A164)) -> 160 | O164: =IF($A164="","",COUNTA($A$5:$A164)) -> 160 | P164: =IF($K164="","",MAX($K$5:K164)) -> 2403.3 | Q164: =IF($K164="","",K164-P164) -> -68.96 | S164: =IF(OR($A164="",$F164=""),"",IF($I164="Pendiente","",ROUND($G164*($F164*0.609-1),2))) -> 1.14 | T164: =IF($A164="","",IFERROR(SUM($S$5:S164),0)) -> 244.77
A165: 46202 | B165: Sportium | C165: IA Akranes - Fram Reykjavik | D165: Totales O/U | E165: Total Under(2.5) | F165: 2.1 | G165: 22 | H165: Normal | I165: Ganada | J165: =IF($A165="","",IF($I165="Ganada",ROUND($G165*($F165-1),2),IF($I165="Medio Ganada",ROUND($G165/2*($F165-1),2),IF($I165="Perdida",IF($H165="Free Bet",0,-$G165),IF($I165="Medio Perdida",IF($H165="Free Bet",0,-$G165/2),IF($I165="Reembolso",IF($R165="","",ROUND($R165-$G165,2)),IF($I165="Anulada",0,""))))))) -> 24.2 | K165: =IF(J165="","",2000+SUM(J$5:J165)) -> 2358.54 | L165: =IF(OR($I165="Ganada",$I165="Perdida",$I165="Medio Ganada",$I165="Medio Perdida"),IF($G165=0,"",J165/$G165),"") -> 1.1 | M165: =IF(OR($A165="",$B165=""),"",COUNTIFS($A$5:A165,A165,$B$5:B165,B165)) -> 5 | N165: =IF($A165="","",COUNTA($A$5:$A165)) -> 161 | O165: =IF($A165="","",COUNTA($A$5:$A165)) -> 161 | P165: =IF($K165="","",MAX($K$5:K165)) -> 2403.3 | Q165: =IF($K165="","",K165-P165) -> -44.76 | S165: =IF(OR($A165="",$F165=""),"",IF($I165="Pendiente","",ROUND($G165*($F165*0.609-1),2))) -> 6.14 | T165: =IF($A165="","",IFERROR(SUM($S$5:S165),0)) -> 250.91
A166: 46202 | B166: Yosport | C166: Germany - Paraguay | D166: Totales O/U | E166: Total Over(2.5) | F166: 1.52 | G166: 23 | H166: Normal | I166: Perdida | J166: =IF($A166="","",IF($I166="Ganada",ROUND($G166*($F166-1),2),IF($I166="Medio Ganada",ROUND($G166/2*($F166-1),2),IF($I166="Perdida",IF($H166="Free Bet",0,-$G166),IF($I166="Medio Perdida",IF($H166="Free Bet",0,-$G166/2),IF($I166="Reembolso",IF($R166="","",ROUND($R166-$G166,2)),IF($I166="Anulada",0,""))))))) -> -23 | K166: =IF(J166="","",2000+SUM(J$5:J166)) -> 2335.54 | L166: =IF(OR($I166="Ganada",$I166="Perdida",$I166="Medio Ganada",$I166="Medio Perdida"),IF($G166=0,"",J166/$G166),"") -> -1 | M166: =IF(OR($A166="",$B166=""),"",COUNTIFS($A$5:A166,A166,$B$5:B166,B166)) -> 1 | N166: =IF($A166="","",COUNTA($A$5:$A166)) -> 162 | O166: =IF($A166="","",COUNTA($A$5:$A166)) -> 162 | P166: =IF($K166="","",MAX($K$5:K166)) -> 2403.3 | Q166: =IF($K166="","",K166-P166) -> -67.76 | S166: =IF(OR($A166="",$F166=""),"",IF($I166="Pendiente","",ROUND($G166*($F166*0.609-1),2))) -> -1.71 | T166: =IF($A166="","",IFERROR(SUM($S$5:S166),0)) -> 249.2
A167: 46203 | B167: Yosport | C167: Otto Virtanen - Ben Shelton | D167: 1X2/ML | E167: Team2 Win - regular time | F167: 1.47 | G167: 22 | H167: Normal | I167: Perdida | J167: =IF($A167="","",IF($I167="Ganada",ROUND($G167*($F167-1),2),IF($I167="Medio Ganada",ROUND($G167/2*($F167-1),2),IF($I167="Perdida",IF($H167="Free Bet",0,-$G167),IF($I167="Medio Perdida",IF($H167="Free Bet",0,-$G167/2),IF($I167="Reembolso",IF($R167="","",ROUND($R167-$G167,2)),IF($I167="Anulada",0,""))))))) -> -22 | K167: =IF(J167="","",2000+SUM(J$5:J167)) -> 2313.54 | L167: =IF(OR($I167="Ganada",$I167="Perdida",$I167="Medio Ganada",$I167="Medio Perdida"),IF($G167=0,"",J167/$G167),"") -> -1 | M167: =IF(OR($A167="",$B167=""),"",COUNTIFS($A$5:A167,A167,$B$5:B167,B167)) -> 1 | N167: =IF($A167="","",COUNTA($A$5:$A167)) -> 163 | O167: =IF($A167="","",COUNTA($A$5:$A167)) -> 163 | P167: =IF($K167="","",MAX($K$5:K167)) -> 2403.3 | Q167: =IF($K167="","",K167-P167) -> -89.76 | S167: =IF(OR($A167="",$F167=""),"",IF($I167="Pendiente","",ROUND($G167*($F167*0.609-1),2))) -> -2.3 | T167: =IF($A167="","",IFERROR(SUM($S$5:S167),0)) -> 246.9
A168: 46203 | B168: Yosport | C168: Iryna Shymanovich - Viktorija Golubic | D168: 1X2/ML | E168: Team2 Win - 3 set | F168: 1.44 | G168: 22 | H168: Normal | I168: Ganada | J168: =IF($A168="","",IF($I168="Ganada",ROUND($G168*($F168-1),2),IF($I168="Medio Ganada",ROUND($G168/2*($F168-1),2),IF($I168="Perdida",IF($H168="Free Bet",0,-$G168),IF($I168="Medio Perdida",IF($H168="Free Bet",0,-$G168/2),IF($I168="Reembolso",IF($R168="","",ROUND($R168-$G168,2)),IF($I168="Anulada",0,""))))))) -> 9.68 | K168: =IF(J168="","",2000+SUM(J$5:J168)) -> 2323.22 | L168: =IF(OR($I168="Ganada",$I168="Perdida",$I168="Medio Ganada",$I168="Medio Perdida"),IF($G168=0,"",J168/$G168),"") -> 0.44 | M168: =IF(OR($A168="",$B168=""),"",COUNTIFS($A$5:A168,A168,$B$5:B168,B168)) -> 2 | N168: =IF($A168="","",COUNTA($A$5:$A168)) -> 164 | O168: =IF($A168="","",COUNTA($A$5:$A168)) -> 164 | P168: =IF($K168="","",MAX($K$5:K168)) -> 2403.3 | Q168: =IF($K168="","",K168-P168) -> -80.08 | S168: =IF(OR($A168="",$F168=""),"",IF($I168="Pendiente","",ROUND($G168*($F168*0.609-1),2))) -> -2.71 | T168: =IF($A168="","",IFERROR(SUM($S$5:S168),0)) -> 244.19
A169: 46203 | B169: Sportium | C169: Birrell, Kimberly - Korneeva, Alina | D169: 1X2/ML | E169: Team2 Win - 3 set, 01 game | F169: 1.5 | G169: 22 | H169: Normal | I169: Perdida | J169: =IF($A169="","",IF($I169="Ganada",ROUND($G169*($F169-1),2),IF($I169="Medio Ganada",ROUND($G169/2*($F169-1),2),IF($I169="Perdida",IF($H169="Free Bet",0,-$G169),IF($I169="Medio Perdida",IF($H169="Free Bet",0,-$G169/2),IF($I169="Reembolso",IF($R169="","",ROUND($R169-$G169,2)),IF($I169="Anulada",0,""))))))) -> -22 | K169: =IF(J169="","",2000+SUM(J$5:J169)) -> 2301.22 | L169: =IF(OR($I169="Ganada",$I169="Perdida",$I169="Medio Ganada",$I169="Medio Perdida"),IF($G169=0,"",J169/$G169),"") -> -1 | M169: =IF(OR($A169="",$B169=""),"",COUNTIFS($A$5:A169,A169,$B$5:B169,B169)) -> 1 | N169: =IF($A169="","",COUNTA($A$5:$A169)) -> 165 | O169: =IF($A169="","",COUNTA($A$5:$A169)) -> 165 | P169: =IF($K169="","",MAX($K$5:K169)) -> 2403.3 | Q169: =IF($K169="","",K169-P169) -> -102.08 | S169: =IF(OR($A169="",$F169=""),"",IF($I169="Pendiente","",ROUND($G169*($F169*0.609-1),2))) -> -1.9 | T169: =IF($A169="","",IFERROR(SUM($S$5:S169),0)) -> 242.29
... A189: 46204 | B189: Pokerstars | C189: sigma olomouc - mfk skalica | D189: Totales O/U | E189: Total Under(0.5) - regular time | F189: 1.44 | G189: 22 | H189: Normal | I189: Ganada | J189: =IF($A189="","",IF($I189="Ganada",ROUND($G189*($F189-1),2),IF($I189="Medio Ganada",ROUND($G189/2*($F189-1),2),IF($I189="Perdida",IF($H189="Free Bet",0,-$G189),IF($I189="Medio Perdida",IF($H189="Free Bet",0,-$G189/2),IF($I189="Reembolso",IF($R189="","",ROUND($R189-$G189,2)),IF($I189="Anulada",0,""))))))) -> 9.68 | K189: =IF(J189="","",2000+SUM(J$5:J189)) -> 2346.68 | L189: =IF(OR($I189="Ganada",$I189="Perdida",$I189="Medio Ganada",$I189="Medio Perdida"),IF($G189=0,"",J189/$G189),"") -> 0.44 | M189: =IF(OR($A189="",$B189=""),"",COUNTIFS($A$5:A189,A189,$B$5:B189,B189)) -> 4 | N189: =IF($A189="","",COUNTA($A$5:$A189)) -> 185 | O189: =IF($A189="","",COUNTA($A$5:$A189)) -> 185 | P189: =IF($K189="","",MAX($K$5:K189)) -> 2403.3 | Q189: =IF($K189="","",K189-P189) -> -56.62 | S189: =IF(OR($A189="",$F189=""),"",IF($I189="Pendiente","",ROUND($G189*($F189*0.609-1),2))) -> -2.71 | T189: =IF($A189="","",IFERROR(SUM($S$5:S189),0)) -> 263.83
A190: 46204 | B190: Pokerstars | C190: Omonia Nicosia - Dinamo Bucuresti 1948 | D190: 1X2/ML | E190: 2 | F190: 1.8 | G190: 18 | H190: Normal | I190: Perdida | J190: =IF($A190="","",IF($I190="Ganada",ROUND($G190*($F190-1),2),IF($I190="Medio Ganada",ROUND($G190/2*($F190-1),2),IF($I190="Perdida",IF($H190="Free Bet",0,-$G190),IF($I190="Medio Perdida",IF($H190="Free Bet",0,-$G190/2),IF($I190="Reembolso",IF($R190="","",ROUND($R190-$G190,2)),IF($I190="Anulada",0,""))))))) -> -18 | K190: =IF(J190="","",2000+SUM(J$5:J190)) -> 2328.68 | L190: =IF(OR($I190="Ganada",$I190="Perdida",$I190="Medio Ganada",$I190="Medio Perdida"),IF($G190=0,"",J190/$G190),"") -> -1 | M190: =IF(OR($A190="",$B190=""),"",COUNTIFS($A$5:A190,A190,$B$5:B190,B190)) -> 5 | N190: =IF($A190="","",COUNTA($A$5:$A190)) -> 186 | O190: =IF($A190="","",COUNTA($A$5:$A190)) -> 186 | P190: =IF($K190="","",MAX($K$5:K190)) -> 2403.3 | Q190: =IF($K190="","",K190-P190) -> -74.62 | S190: =IF(OR($A190="",$F190=""),"",IF($I190="Pendiente","",ROUND($G190*($F190*0.609-1),2))) -> 1.73 | T190: =IF($A190="","",IFERROR(SUM($S$5:S190),0)) -> 265.56
A191: 46204 | B191: Yosport | C191: Brandon Nakashima - Jan-Lennard Struff | D191: 1X2/ML | E191: Team1 Win - regular time | F191: 1.4 | G191: 22 | H191: Normal | I191: Perdida | J191: =IF($A191="","",IF($I191="Ganada",ROUND($G191*($F191-1),2),IF($I191="Medio Ganada",ROUND($G191/2*($F191-1),2),IF($I191="Perdida",IF($H191="Free Bet",0,-$G191),IF($I191="Medio Perdida",IF($H191="Free Bet",0,-$G191/2),IF($I191="Reembolso",IF($R191="","",ROUND($R191-$G191,2)),IF($I191="Anulada",0,""))))))) -> -22 | K191: =IF(J191="","",2000+SUM(J$5:J191)) -> 2306.68 | L191: =IF(OR($I191="Ganada",$I191="Perdida",$I191="Medio Ganada",$I191="Medio Perdida"),IF($G191=0,"",J191/$G191),"") -> -1 | M191: =IF(OR($A191="",$B191=""),"",COUNTIFS($A$5:A191,A191,$B$5:B191,B191)) -> 1 | N191: =IF($A191="","",COUNTA($A$5:$A191)) -> 187 | O191: =IF($A191="","",COUNTA($A$5:$A191)) -> 187 | P191: =IF($K191="","",MAX($K$5:K191)) -> 2403.3 | Q191: =IF($K191="","",K191-P191) -> -96.62 | S191: =IF(OR($A191="",$F191=""),"",IF($I191="Pendiente","",ROUND($G191*($F191*0.609-1),2))) -> -3.24 | T191: =IF($A191="","",IFERROR(SUM($S$5:S191),0)) -> 262.32
A192: 46204 | B192: Sportium | C192: Bencic, Belinda - Wang, Xinyu | D192: Hándicap | E192: Asian Handicap2(5.5) - regular timev | F192: 1.4 | G192: 22 | H192: Normal | I192: Perdida | J192: =IF($A192="","",IF($I192="Ganada",ROUND($G192*($F192-1),2),IF($I192="Medio Ganada",ROUND($G192/2*($F192-1),2),IF($I192="Perdida",IF($H192="Free Bet",0,-$G192),IF($I192="Medio Perdida",IF($H192="Free Bet",0,-$G192/2),IF($I192="Reembolso",IF($R192="","",ROUND($R192-$G192,2)),IF($I192="Anulada",0,""))))))) -> -22 | K192: =IF(J192="","",2000+SUM(J$5:J192)) -> 2284.68 | L192: =IF(OR($I192="Ganada",$I192="Perdida",$I192="Medio Ganada",$I192="Medio Perdida"),IF($G192=0,"",J192/$G192),"") -> -1 | M192: =IF(OR($A192="",$B192=""),"",COUNTIFS($A$5:A192,A192,$B$5:B192,B192)) -> 4 | N192: =IF($A192="","",COUNTA($A$5:$A192)) -> 188 | O192: =IF($A192="","",COUNTA($A$5:$A192)) -> 188 | P192: =IF($K192="","",MAX($K$5:K192)) -> 2403.3 | Q192: =IF($K192="","",K192-P192) -> -118.62 | S192: =IF(OR($A192="",$F192=""),"",IF($I192="Pendiente","",ROUND($G192*($F192*0.609-1),2))) -> -3.24 | T192: =IF($A192="","",IFERROR(SUM($S$5:S192),0)) -> 259.08
A193: 46204 | B193: Sportium | C193: Varillas Patino-Samudio, Juan Pablo - Magadan, Alan | D193: 1X2/ML | E193: Team2 Win - 2 set, 08 game | F193: 1.48 | G193: 22 | H193: Normal | I193: Perdida | J193: =IF($A193="","",IF($I193="Ganada",ROUND($G193*($F193-1),2),IF($I193="Medio Ganada",ROUND($G193/2*($F193-1),2),IF($I193="Perdida",IF($H193="Free Bet",0,-$G193),IF($I193="Medio Perdida",IF($H193="Free Bet",0,-$G193/2),IF($I193="Reembolso",IF($R193="","",ROUND($R193-$G193,2)),IF($I193="Anulada",0,""))))))) -> -22 | K193: =IF(J193="","",2000+SUM(J$5:J193)) -> 2262.68 | L193: =IF(OR($I193="Ganada",$I193="Perdida",$I193="Medio Ganada",$I193="Medio Perdida"),IF($G193=0,"",J193/$G193),"") -> -1 | M193: =IF(OR($A193="",$B193=""),"",COUNTIFS($A$5:A193,A193,$B$5:B193,B193)) -> 5 | N193: =IF($A193="","",COUNTA($A$5:$A193)) -> 189 | O193: =IF($A193="","",COUNTA($A$5:$A193)) -> 189 | P193: =IF($K193="","",MAX($K$5:K193)) -> 2403.3 | Q193: =IF($K193="","",K193-P193) -> -140.62 | S193: =IF(OR($A193="",$F193=""),"",IF($I193="Pendiente","",ROUND($G193*($F193*0.609-1),2))) -> -2.17 | T193: =IF($A193="","",IFERROR(SUM($S$5:S193),0)) -> 256.91
A194: 46204 | B194: Pokerstars | C194: Denmark U19 - Spain U19 | D194: Totales O/U | E194: Total Under(2.5) - regular time | F194: 1.8 | G194: 18 | H194: Normal | I194: Perdida | J194: =IF($A194="","",IF($I194="Ganada",ROUND($G194*($F194-1),2),IF($I194="Medio Ganada",ROUND($G194/2*($F194-1),2),IF($I194="Perdida",IF($H194="Free Bet",0,-$G194),IF($I194="Medio Perdida",IF($H194="Free Bet",0,-$G194/2),IF($I194="Reembolso",IF($R194="","",ROUND($R194-$G194,2)),IF($I194="Anulada",0,""))))))) -> -18 | K194: =IF(J194="","",2000+SUM(J$5:J194)) -> 2244.68 | L194: =IF(OR($I194="Ganada",$I194="Perdida",$I194="Medio Ganada",$I194="Medio Perdida"),IF($G194=0,"",J194/$G194),"") -> -1 | M194: =IF(OR($A194="",$B194=""),"",COUNTIFS($A$5:A194,A194,$B$5:B194,B194)) -> 6 | N194: =IF($A194="","",COUNTA($A$5:$A194)) -> 190 | O194: =IF($A194="","",COUNTA($A$5:$A194)) -> 190 | P194: =IF($K194="","",MAX($K$5:K194)) -> 2403.3 | Q194: =IF($K194="","",K194-P194) -> -158.62 | S194: =IF(OR($A194="",$F194=""),"",IF($I194="Pendiente","",ROUND($G194*($F194*0.609-1),2))) -> 1.73 | T194: =IF($A194="","",IFERROR(SUM($S$5:S194),0)) -> 258.64
A195: 46204 | B195: Pokerstars | C195: Solothurn - Young Boys II | D195: 1X2/ML | E195: 1 | F195: 2.1 | G195: 18 | H195: Normal | I195: Ganada | J195: =IF($A195="","",IF($I195="Ganada",ROUND($G195*($F195-1),2),IF($I195="Medio Ganada",ROUND($G195/2*($F195-1),2),IF($I195="Perdida",IF($H195="Free Bet",0,-$G195),IF($I195="Medio Perdida",IF($H195="Free Bet",0,-$G195/2),IF($I195="Reembolso",IF($R195="","",ROUND($R195-$G195,2)),IF($I195="Anulada",0,""))))))) -> 19.8 | K195: =IF(J195="","",2000+SUM(J$5:J195)) -> 2264.48 | L195: =IF(OR($I195="Ganada",$I195="Perdida",$I195="Medio Ganada",$I195="Medio Perdida"),IF($G195=0,"",J195/$G195),"") -> 1.1 | M195: =IF(OR($A195="",$B195=""),"",COUNTIFS($A$5:A195,A195,$B$5:B195,B195)) -> 7 | N195: =IF($A195="","",COUNTA($A$5:$A195)) -> 191 | O195: =IF($A195="","",COUNTA($A$5:$A195)) -> 191 | P195: =IF($K195="","",MAX($K$5:K195)) -> 2403.3 | Q195: =IF($K195="","",K195-P195) -> -138.82 | S195: =IF(OR($A195="",$F195=""),"",IF($I195="Pendiente","",ROUND($G195*($F195*0.609-1),2))) -> 5.02 | T195: =IF($A195="","",IFERROR(SUM($S$5:S195),0)) -> 263.66
A196: 46204 | B196: Pokerstars | C196: KORNEUBURG ASC MARATHON - Wiener Victoria | D196: Totales O/U | E196: Total Under(2.5) - regular time | F196: 1.83 | G196: 18 | H196: Normal | I196: Perdida | J196: =IF($A196="","",IF($I196="Ganada",ROUND($G196*($F196-1),2),IF($I196="Medio Ganada",ROUND($G196/2*($F196-1),2),IF($I196="Perdida",IF($H196="Free Bet",0,-$G196),IF($I196="Medio Perdida",IF($H196="Free Bet",0,-$G196/2),IF($I196="Reembolso",IF($R196="","",ROUND($R196-$G196,2)),IF($I196="Anulada",0,""))))))) -> -18 | K196: =IF(J196="","",2000+SUM(J$5:J196)) -> 2246.48 | L196: =IF(OR($I196="Ganada",$I196="Perdida",$I196="Medio Ganada",$I196="Medio Perdida"),IF($G196=0,"",J196/$G196),"") -> -1 | M196: =IF(OR($A196="",$B196=""),"",COUNTIFS($A$5:A196,A196,$B$5:B196,B196)) -> 8 | N196: =IF($A196="","",COUNTA($A$5:$A196)) -> 192 | O196: =IF($A196="","",COUNTA($A$5:$A196)) -> 192 | P196: =IF($K196="","",MAX($K$5:K196)) -> 2403.3 | Q196: =IF($K196="","",K196-P196) -> -156.82 | S196: =IF(OR($A196="",$F196=""),"",IF($I196="Pendiente","",ROUND($G196*($F196*0.609-1),2))) -> 2.06 | T196: =IF($A196="","",IFERROR(SUM($S$5:S196),0)) -> 265.72
A197: 46204 | B197: Sportium | C197: Boston Red Sox - Washington Nationals | D197: 1X2/ML | E197: Team2 Win | F197: 1.55 | G197: 22 | H197: Normal | I197: Ganada | J197: =IF($A197="","",IF($I197="Ganada",ROUND($G197*($F197-1),2),IF($I197="Medio Ganada",ROUND($G197/2*($F197-1),2),IF($I197="Perdida",IF($H197="Free Bet",0,-$G197),IF($I197="Medio Perdida",IF($H197="Free Bet",0,-$G197/2),IF($I197="Reembolso",IF($R197="","",ROUND($R197-$G197,2)),IF($I197="Anulada",0,""))))))) -> 12.1 | K197: =IF(J197="","",2000+SUM(J$5:J197)) -> 2258.58 | L197: =IF(OR($I197="Ganada",$I197="Perdida",$I197="Medio Ganada",$I197="Medio Perdida"),IF($G197=0,"",J197/$G197),"") -> 0.55 | M197: =IF(OR($A197="",$B197=""),"",COUNTIFS($A$5:A197,A197,$B$5:B197,B197)) -> 6 | N197: =IF($A197="","",COUNTA($A$5:$A197)) -> 193 | O197: =IF($A197="","",COUNTA($A$5:$A197)) -> 193 | P197: =IF($K197="","",MAX($K$5:K197)) -> 2403.3 | Q197: =IF($K197="","",K197-P197) -> -144.72 | S197: =IF(OR($A197="",$F197=""),"",IF($I197="Pendiente","",ROUND($G197*($F197*0.609-1),2))) -> -1.23 | T197: =IF($A197="","",IFERROR(SUM($S$5:S197),0)) -> 264.49
A198: 46204 | B198: GoldenBull | C198: Rafael Jodar - Pablo Carreno Busta | D198: 1X2/ML | E198: 1 | F198: 1.88 | G198: 18 | H198: Normal | I198: Ganada | J198: =IF($A198="","",IF($I198="Ganada",ROUND($G198*($F198-1),2),IF($I198="Medio Ganada",ROUND($G198/2*($F198-1),2),IF($I198="Perdida",IF($H198="Free Bet",0,-$G198),IF($I198="Medio Perdida",IF($H198="Free Bet",0,-$G198/2),IF($I198="Reembolso",IF($R198="","",ROUND($R198-$G198,2)),IF($I198="Anulada",0,""))))))) -> 15.84 | K198: =IF(J198="","",2000+SUM(J$5:J198)) -> 2274.42 | L198: =IF(OR($I198="Ganada",$I198="Perdida",$I198="Medio Ganada",$I198="Medio Perdida"),IF($G198=0,"",J198/$G198),"") -> 0.88 | M198: =IF(OR($A198="",$B198=""),"",COUNTIFS($A$5:A198,A198,$B$5:B198,B198)) -> 5 | N198: =IF($A198="","",COUNTA($A$5:$A198)) -> 194 | O198: =IF($A198="","",COUNTA($A$5:$A198)) -> 194 | P198: =IF($K198="","",MAX($K$5:K198)) -> 2403.3 | Q198: =IF($K198="","",K198-P198) -> -128.88 | S198: =IF(OR($A198="",$F198=""),"",IF($I198="Pendiente","",ROUND($G198*($F198*0.609-1),2))) -> 2.61 | T198: =IF($A198="","",IFERROR(SUM($S$5:S198),0)) -> 267.1
A199: 46204 | B199: Pokerstars | C199: New York Yankees - Detroit Tigers | D199: Totales O/U | E199: Total Over(3.5) | F199: 2.05 | G199: 18 | H199: Normal | I199: Ganada | J199: =IF($A199="","",IF($I199="Ganada",ROUND($G199*($F199-1),2),IF($I199="Medio Ganada",ROUND($G199/2*($F199-1),2),IF($I199="Perdida",IF($H199="Free Bet",0,-$G199),IF($I199="Medio Perdida",IF($H199="Free Bet",0,-$G199/2),IF($I199="Reembolso",IF($R199="","",ROUND($R199-$G199,2)),IF($I199="Anulada",0,""))))))) -> 18.9 | K199: =IF(J199="","",2000+SUM(J$5:J199)) -> 2293.32 | L199: =IF(OR($I199="Ganada",$I199="Perdida",$I199="Medio Ganada",$I199="Medio Perdida"),IF($G199=0,"",J199/$G199),"") -> 1.05 | M199: =IF(OR($A199="",$B199=""),"",COUNTIFS($A$5:A199,A199,$B$5:B199,B199)) -> 9 | N199: =IF($A199="","",COUNTA($A$5:$A199)) -> 195 | O199: =IF($A199="","",COUNTA($A$5:$A199)) -> 195 | P199: =IF($K199="","",MAX($K$5:K199)) -> 2403.3 | Q199: =IF($K199="","",K199-P199) -> -109.98 | S199: =IF(OR($A199="",$F199=""),"",IF($I199="Pendiente","",ROUND($G199*($F199*0.609-1),2))) -> 4.47 | T199: =IF($A199="","",IFERROR(SUM($S$5:S199),0)) -> 271.57
...

Sheet Gráficas
A1: Evolución del Bankroll
A42: Drawdown — Picos y Valles
A84: EV+ Histórico Acumulado
A126: Beneficio por Casa (€)
